<?xml version="1.0" encoding="UTF-8"?>
<!DOCTYPE kalliopework SYSTEM "../../data/kalliopework.dtd">
<kalliopework id="1810a" author="grundtvig" status="incomplete" type="poetry">
<workhead>
   <title>Idunna</title>
   <year>1810</year>
</workhead>
<workbody>

<poem id="grundtvig2019122905">
<head>
    <title>Jørgen Sorterup</title>
    <firstline>O, Du gamle, kække Skjald!</firstline>
    <notes>
        <note>Teksten følger <a href="http://www.grundtvigsværker.dk">grundtvigsværker.dk</a>.</note>
    </notes>
    <keywords>sorterup</keywords>
</head>
<body>
<nonum><right><small>Han haver sig baaret en Søn under Ø,</small></right></nonum>
<nonum><right><small>Som haver den Skebne, han aldrig skal dø,</small></right></nonum>
<nonum><right><small>Og aldrig sin Klædning opslide.</small></right></nonum>
<nonum><right><small><i>Sorterups Heltesange.</i></small></right></nonum>

O, Du gamle, kække Skjald!
Mindes skal Du af den unge;
Dansk Du var i Tonefald,
Dansk af Æt, af Kraft og Tunge.
Naar om Kæmperne i Nord,
Du din Tordensang lod høre,
Da sig maatte vist i Jord
Nordens gamle Kæmper røre.

Roms den visne Gudeflok
Vilde Du i Sang ei dyrke,
Agted den for Sten og Stok,
Uden Magt og uden Størke,
Zebaoth Du Offer bar,
Hvergang Du i Sang Dig øved.
I Dig selv en Guddom var,
Guderne Du ei behøved.

Dog det gamle Bjarkemaal
Tyktes Dig en herlig Flamme,
Gamle danske Mænd i Staal
Kaldte Du din egen Stamme,
Deres Pris Du hørte helst,
Og det glædte Dig i Sinde,
At ved Skjaldens Kvad var frelst
Odins og Kong Frodes Minde.

Varslende stod Axelvold,
Da Du blev til Verden baaret,
Dig saa stolt en Helteold
Til sin Ligskjald havde kaaret:
Juler paa det danske Hav
Saae Du Manddomsværker øve,
Og Du sang, Dig ned i Grav,
Om en Sehsted, Gyldenløve.

Du var Bragurs ægte Søn,
Dog dit Kvad os gik af Minde,
Derfor maa saa tit i Løn
Mine bittre Taarer rinde:
Graad og Latter, store Skjald!
Kvalte tit din høie Stemme.
Ak, men dybt var Danmarks Fald,
Da det kunde Dig forglemme.

Døvet blev din Heltesang,
Intet den dog fuldt neddæmper,
Jordes Du og mangengang,
Staar Du op med dine Kæmper;
Du med Sang, og de med Sværd
Samme Idræt ville øve:
Vække Mænd, som gange nær
Rabe, Sehsted, Gyldenløve.

Lirespil om Paarses Færd,
Det blev Danmarks Heltekvæde,
Daaden blev og Sangen værd,
Danmarks Flaade vi begræde;
Hist, hvor Jul i Kjøgebugt,
Seierrig med Fjenden droges,
Der saae vi de Danskes Flugt:
Gamle Axelstad indtoges.

Men naar Dannemark engang,
Vaagner af sin lange Dvale,
Atter tone skal din Sang,
Kæmpeskjald! i høie Sale.
Glæd Dig, Skjald! den Stund er nær
Baal nedstyrtes, Herren vinder,
Alt sig hvæsser Danmarks Sværd,
Hjertet higer, Gud det finder.    
</body>
</poem>

</workbody>
</kalliopework>
