<?xml version="1.0" encoding="UTF-8"?>
<!DOCTYPE kalliopework SYSTEM "../../data/kalliopework.dtd">
<kalliopework id="1845" author="gerson" status="incomplete" type="poetry">
<workhead>
   <title>Digte for Børn</title>
   <year>1845</year>
   <quality>korrektur1</quality>
   <cvs-timestamp>$Id$</cvs-timestamp>
</workhead>
<workbody>

<poem id="gerson1999031801">
<head>
   <title>Den største Mand</title>
   <toctitle>Den største Mand</toctitle>
   <indextitle>Den største Mand</indextitle>
   <firstline>En lille Nisse reiste</firstline>
   <quality>korrektur1</quality>
</head>
<body>
En lille Nisse reiste
Med Extrapost fra Land til Land,
Hans Agt det var at hilse
Paa Verdens største Mand.

Han kom til Stormogulen
Og der hvor Kæmpekaalen groer,
Men mellem alle Kæmper
Ham tyktes Ingen stor.

Da gik han hen til Havet,
Og stirred i det klare Vand; -
Han smilte, thi nu havde
Han seet den største Mand.
</body>
</poem>
</workbody>
</kalliopework>
