<?xml version="1.0" encoding="UTF-8"?>
<!DOCTYPE kalliopework SYSTEM "../../data/kalliopework.dtd">
<kalliopework id="andre" author="morike" status="incomplete" type="poetry">
<workhead>
   <title>Andre digte</title>
   <year>?</year>
   <cvs-timestamp>$Id$</cvs-timestamp>
</workhead>
<workbody>

<poem id="morike2001102408">
<head>
   <title>Theokrit</title>
   <toctitle>Theokrit</toctitle>
   <indextitle>Theokrit</indextitle>
   <firstline>Sei, o Theokritos, mir, du Anmutsvollster, gepriesen!</firstline>
</head>
<body>
Sei, o Theokritos, mir, du Anmutsvollster, gepriesen!
Lieblich bist du zuerst, aber auch herrlich fuerwahr.
Wenn du die Chariten schickst in die Goldpaläste der Reichen,
Unbeschenkt kehren sie dir, nackenden Fusses, zurueck.
Muessig sitzen sie wieder im ärmlichen Hause des Dichters,
Auf die frierenden Knie traurig die Stirne gesenkt.
Oder die Jungfrau fuehre mir vor, die, rasend in Liebe,
Da ihr der juengling entfloh, Hekates Kuenste versucht.
Oder besinge den jungen Herakles, welchem zur Wiege
Dienet der eherne Schild, wo er die Schlangen erwuergt:
Klangvoll fährst du dahin! dich kränzte Kalliope selber,
Aber bescheiden, ein Hirt, kehrst du zur Flöte zurueck.
</body>
</poem>

<poem id="morike2001102409">
<head>
   <title>Meiner Schwester</title>
   <subtitle>Sommer 1841</subtitle>
   <toctitle>Meiner Schwester</toctitle>
   <indextitle>Meiner Schwester</indextitle>
   <firstline>Blättchen, das im losen Spiel</firstline>
   <notes>
      <note>,,Nach dem Tode der Mutter, mit einem Blatt von der Birke zwischen dem Pfarrhaus und dem Kirchhof zu Cleversulzbach.''</note>
   </notes>
</head>
<body>
»Blättchen, das im losen Spiel
Winde durch die Lüfte tragen,
Blättchen, kannst du mir nicht sagen,
Wo ist deiner Wandrung Ziel?«

Ach ich weiß ein frommes Kind,
Dem möcht ich mich gern verbinden,
Und kann doch den Weg nicht finden,
So verstürmte mich der Wind.

Als ich aus der Knospe mich
Vor den Veilchen, früh, gerungen,
Kam das Liebchen oft gesungen
Durch den Garten morgendlich.

Aber da sich, glatt und schön,
Tät mein grünes Herzlein dehnen,
Sah ich sie in bittern Tränen
Unter unsern Zweigen stehn.

Und dort drüben überm Hag,
Steht das Röslein, steht die Weide,
Dahin wallte sie in Leide
Mir vorüber jeden Tag.

Freut' auch mich nichts weiter mehr,
Nicht die süße Maiensonne,
Bienenton und Schaukelwonne,
Keine kühle Mondnacht mehr.

Also welkt ich vor der Zeit,
Bin, bevor der Herbst gekommen,
Aus der Mutter Hut genommen
Und von der Geliebten weit.

Dürft ich zu ihr, ach wieviel
Sagt ich ihr von Lust und Schmerzen!
Und an dem getreusten Herzen
Fänd ich meiner Wandrung Ziel.
</body>
</poem>

<poem id="morike2001102410">
<head>
   <title>Nixe Binsefuß</title>
   <toctitle>Nixe Binsefuß</toctitle>
   <indextitle>Nixe Binsefuß</indextitle>
   <firstline>Des Wassermanns sein Töchterlein</firstline>
</head>
<body>
Des Wassermanns sein Töchterlein
tanzt auf dem Eis im Vollmondschein,
sie singt und lachet sonder Scheu
wohl an des Fischers Haus vorbei.

,,Ich bin die Jungfer Binsefuß
und meine Fisch' wohl hüten muß;
meine Fisch', die sind im Kasten,
sie haben kalte Fasten;
von Böhmerglas mein Kasten ist,
da zähl' ich sie zu jeder Frist.

Gelt, Fischer-Matz? gelt, alter Tropf,
dir will der Winter nicht in Kopf?
Komm mir mit deinen Netzen!
Die will ich schön zerfetzen!
Dein Mägdlein zwar ist fromm und gut,
ihr Schatz ein braves Jägerblut.

Drum häng' ich ihr, zum Hochzeitsstrauß,
ein schilfen Kränzlein vor das Haus
und einen Hecht, von Silber schwer,
er stammt von König Artus her,
ein Zwergen-Goldschmieds-Meisterstück,
wer's hat, dem bringt es eitel Glück:
Er läßt sich schuppen Jahr für Jahr,
da sind's fünfhundert Gröschlein bar.

Ade, mein Kind! Ade für heut'!
Der Morgenhahn im Dorfe schreit.''
</body>
</poem>

<poem id="morike2001102411">
<head>
   <title>Neue Liebe</title>
   <toctitle>Neue Liebe</toctitle>
   <indextitle>Neue Liebe</indextitle>
   <firstline>Kann auch ein Mensch des andern auf der Erde</firstline>
</head>
<body>
Kann auch ein Mensch des andern auf der Erde
Ganz, wie er möchte, sein?
- In langer Nacht bedacht ich mirs, und musste sagen, nein!

So kann ich niemands heissen auf der Erde,
Und niemand wäre mein?
- Aus Finsternissen hell in mir aufzueckt ein Freudenschein:

Sollt ich mit Gott nicht können sein,
So wie ich möchte, Mein und Dein?
Was hielte mich, dass ichs nicht heute werde?

Ein suesses Schrecken geht durch mein Gebein!
Mich wundert, dass es mir ein Wunder wollte sein,
Gott selbst zu eigen haben auf der Erde!
</body>
</poem>

<poem id="morike2001102412">
<head>
   <title>Muse und Dichter</title>
   <toctitle>Muse und Dichter</toctitle>
   <indextitle>Muse und Dichter</indextitle>
   <firstline>Krank nun vollends und matt! Und du, o Himmlische, willst mir</firstline>
</head>
<body>
»Krank nun vollends und matt! Und du, o Himmlische, willst mir
    Auch schon verstummen - o was deutet dies Schweigen mir an?
Gib die Leier!« - »Nicht doch, dir ist die Ruhe geboten.
    Schlafe! träume nur! still ruf ich dir Hülfe herab.
Deinem Haupte noch blühet ein Kranz; und sei es zum Leben,
    Sei's zum Tode, getrost! meine Hand windet ihn dir.«
»Keinen Lorbeer will ich, die kalte Stirne zu schmücken:
    Laß mich leben, und gib fröhliche Blumen zum Strauß!«
</body>
</poem>

<poem id="morike2001102413">
<head>
   <title>Epistel</title>
   <toctitle>Epistel</toctitle>
   <indextitle>Epistel</indextitle>
   <firstline>Wie sich dein neuer Pöt in unserem Kreise gefalle</firstline>
</head>
<body>
Wie sich dein neuer Pöt in unserem Kreise gefalle?
Nicht zum besten. Er meint, man verstünd ihn eben auch hier nicht.
Jetzo hat er ein griechisches Epos, hör ich, die Argo-
nauten, heroische Form, auf dem Amboß. Segn' es der Gott ihm,
Aber zu lesen begehr ich es nicht. Glaub mir, das ist auch so
Eins von den sauren Genies, dergleichen wir mehrere kennen.
Wortkarg streicht er den Schnurrbart sich, wie verstimmt und befangen,
Wenn man des Trefflichsten irgend gedenkt von den Alten und Neuen;
Oder er mäkelt daran mit kleinlichem Tadel, von fern erst,
Bis er, hitziger werdend im Streit, Maßloses daherschwatzt
Und wie ein stätischer Esel hinausschlägt, wo es auch hintrifft.
Das sind schlimme Symptome. - Vernimm ein homerisches Gleichnis
(Pflegten wir doch vormals in parodischer Laune zuweilen
Stundenlang nach der Weise des göttlichen Alten zu reden)
Gleichwie die gelbliche Birne zur Herbstzeit, wenn sie gereifet
Fiel vom Ast und im Fall von der dornigen Hecke verwundet
Liegt am Boden, alsbald mit schwärmenden Wespen bedeckt ist,
Welche sie rings aushöhlen, die gierigen Kiefer bewegend
Also strotzet sein Herz von wilden Gedanken der Ehrsucht
Und des verzehrenden Neids. Ihn blendete völlig ein Dämon.
</body>
</poem>

<poem id="morike2001102414">
<head>
   <title>Auf den Tod eines Vogels</title>
   <toctitle>Auf den Tod eines Vogels</toctitle>
   <indextitle>Auf den Tod eines Vogels</indextitle>
   <firstline>O Vogel, ist es aus mit dir</firstline>
</head>
<body>
O Vogel, ist es aus mit dir?
Krank uebergab ich dich Barmherzgen-Schwester-Händen,
Ob sie vielleicht noch dein Verhängnis wenden;
So war denn keine Hilfe hier?
Zwei Augen, schwarz als wie die deinen,
Sah ich mit deinem Blick sich einen,
Und gleich erlosch sein schönes Licht.
Hast du von ihnen Leids erfahren?
Wohlan, wenn <i>sie</i> dir tödlich waren,
So war dein Tod so bitter nicht!
</body>
</poem>

<poem id="morike2001102415">
<head>
   <title>Antike Poesie</title>
   <toctitle>Antike Poesie</toctitle>
   <indextitle>Antike Poesie</indextitle>
   <firstline>Ich sah den Helikon in Wolkendunst</firstline>
   <keywords>sonnet</keywords>
</head>
<body>
Ich sah den Helikon in Wolkendunst,
Nur kaum berührt vom ersten Sonnenstrahle:
Schau! Jetzo stehen hoch mit einem Male
Die Gipfel dort in Morgenrötebrunst.

Hier unten spricht von keuscher Musen Gunst
Der heilge Quell im dunkelgrünen Tale;
Wer aber schöpft mit reiner Opferschale,
Wie einst, den echten Tau der alten Kunst?

Wie? soll ich endlich keinen Meister sehn?
Will keiner mehr den alten Lorbeer pflücken? -
Da sah ich Iphigeniens Dichter stehn:

Er ist's, an dessen Blick sich diese Höhn
So zauberhaft, so sonnewarm erquicken.
Er geht, und frostig rauhe Lüfte wehn.
</body>
</poem>

<poem id="morike2001102416">
<head>
   <title>Nachts am Schreibepult</title>
   <toctitle>Nachts am Schreibepult</toctitle>
   <indextitle>Nachts am Schreibepult</indextitle>
   <firstline>Primel und Stern und Syringe, von einsamer Kerze beleuchtet</firstline>
</head>
<body>
Primel und Stern und Syringe, von einsamer Kerze beleuchtet,
Hier im Glase, wie fremd blickt ihr, wie feenhaft, her!
Sonne schien, als die Liebste euch trug, da wart ihr so freudig:
Mitternacht summt nun um euch, ach! und kein Liebchen ist hier.
</body>
</poem>

<poem id="morike2001102417">
<head>
   <title>Sehnsucht</title>
   <toctitle>Sehnsucht</toctitle>
   <indextitle>Sehnsucht</indextitle>
   <firstline>In dieser Winterfruehe</firstline>
</head>
<body>
In dieser Winterfruehe
Wie ist mir doch zumut!
O Morgenrot, ich gluehe
Von deinem Jugendblut.

Es glueht der alte Felsen,
Und Wald und Burg zumal,
Berauschte Nebel wälzen
Sich jäh hinab das Tal.

Mit tatenfroher Eile
Erhebt sich Geist und Sinn,
Und fluegelt goldne Pfeile
Durch alle Ferne hin.

Auf Zinnen möcht ich springen,
In alter Fuersten Schloss,
Möcht hohe Lieder singen,
Mich schwingen auf das Ross!

Und stolzen Siegeswagen
Stuerzt ich mich brausend nach,
Die Harfe wird zerschlagen,
Die nur von Liebe sprach.

- Wie? schwärmst du so vermessen,
Herz, hast du nicht bedacht,
Hast du mit eins vergessen,
Was dich so trunken macht?

Ach, wohl! was aus mir singet,
Ist nur der Liebe Glueck!
Die wirren Töne schlinget
Sie sanft in sich zurueck.

Was hilft, was hilft mein Sehnen?
Geliebte, wärst du hier!
In tausend Freudetränen
Verging' die Erde mir.
</body>
</poem>

<poem id="morike2001102418">
<head>
   <title>Weihgeschenk</title>
   <toctitle>Weihgeschenk</toctitle>
   <indextitle>Weihgeschenk</indextitle>
   <firstline>Von kunstfertigen Händen geschält, drei Äpfelchen, zierlich</firstline>
</head>
<body>
Von kunstfertigen Händen geschält, drei Äpfelchen, zierlich,
    Hängend an <i>einem</i> Zweig, den noch ein Blättchen umgrünt;
Weiß wie das Wachs ihr Fleisch, von lieblicher Röte durchschimmert;
    Dicht aneinandergeschmiegt, bärgen die nackten sich gern.
Schämet euch nicht, ihr Schwestern! euch hat ein Mädchen entkleidet,
    Und den Chariten fromm bringet ein Sänger euch dar.
</body>
</poem>

<poem id="morike2001102419">
<head>
   <title>Zwiespalt</title>
   <subtitle>Nach Catull</subtitle>
   <toctitle>Zwiespalt</toctitle>
   <indextitle>Zwiespalt</indextitle>
   <firstline>Hassen und lieben zugleich muss ich. - Wie das? - Wenn ichs wuesste!</firstline>
   <notes>
      <note>Efter Gaius Valerius Catullus' digt nr. LXXXV: Odi et amo, quare id faciam, fortasse requiris? / nescio, sed fieri sentio et excrucior.</note>
   </notes>
</head>
<body>
Hassen und lieben zugleich muss ich. - Wie das? - Wenn ichs wuesste!
Aber ich fuehls, und das Herz möchte zerreissen in mir.
</body>
</poem>

<poem id="morike2001102420">
<head>
   <title>Wo find ich Trost?</title>
   <toctitle>Wo find ich Trost?</toctitle>
   <indextitle>Wo find ich Trost?</indextitle>
   <firstline>Eine Liebe kenn ich, die ist treu</firstline>
</head>
<body>
Eine Liebe kenn ich, die ist treu,
War getreu, solang ich sie gefunden,
Hat mit tiefem Seufzen immer neu,
Stets versöhnlich, sich mit mir verbunden.

Welcher einst mit himmlischem Gedulden
Bitter bittern Todestropfen trank,
Hing am Kreuz und büßte mein Verschulden,
Bis es in ein Meer von Gnade sank.

Und was ist's nun, daß ich traurig bin,
Daß ich angstvoll mich am Boden winde?
Frage: »Hüter, ist die Nacht bald hin?«
Und: »was rettet mich von Tod und Sünde?«

Arges Herze! ja gesteh es nur,
Du hast wieder böse Lust empfangen;
Frommer Liebe, frommer Treue Spur,
Ach, das ist auf lange nun vergangen.

Ja, das ist's auch, daß ich traurig bin,
Daß ich angstvoll mich am Boden winde!
Hüter, Hüter, ist die Nacht bald hin?
Und was rettet mich von Tod und Sünde?
</body>
</poem>

<poem id="morike2001102421">
<head>
   <title>Erinna an Sappho</title>
   <toctitle>Erinna an Sappho</toctitle>
   <indextitle>Erinna an Sappho</indextitle>
   <firstline>Vielfach sind zum Hades die Pfade, heisst ein</firstline>
</head>
<body>
,,Vielfach sind zum Hades die Pfade'', heisst ein
Altes Liedchen - ,,und einen gehst du selber,
Zweifle nicht!'' Wer, suesseste Sappho, zweifelt?
Sagt es nicht jeglicher Tag?
Doch den Lebenden haftet nur leicht im Busen
Solch ein Wort, und dem Meer anwohnend ein Fischer von Kind auf
Hört im stumpferen Ohr der Wogen Geräusch nicht mehr.
- Wundersam aber erschrak mir heute das Herz. Vernimm!

Sonniger Morgenglanz im Garten,
Ergossen um der Bäume Wipfel,
Lockte die Langschläferin (denn so schaltest du juengst Erinna!)
Frueh vom schwueligen Lager hinweg.
Stille war mein Gemuet; in den Adern aber
Unstet klopfte das Blut bei der Wangen Blässe.

Als ich am Putztisch jetzo die Flechten lös'te,
Dann mit nardeduftendem Kamm vor der Stirn den Haar-
Schleier teilte, - seltsam betraf mich im Spiegel Blick in Blick.
Augen, sagt ich, ihr Augen, was wollt ihr?
Du, mein Geist, heute noch sicher behaus't da drinne,
Lebendigen Sinnen traulich vermählt,
Wie mit fremdendem Ernst, lächelnd halb, ein Dämon,
Nickst du mich an, Tod weissagend!
- Ha, da mit eins durchzuckt' es mich
Wie Wetterschein! wie wenn schwarzgefiedert ein tödlicher Pfeil
Streifte die Schläfe hart vorbei,
Dass ich, die Hände gedeckt aufs Antlitz, lange
Staunend blieb, in die nachtschaurige Kluft schwindelnd hinab.

Und das eigene Todesgeschick erwog ich;
Trockenen Augs noch erst,
Bis da ich dein, o Sappho, dachte,
Und der Freundinnen all,
Und anmutiger Musenkunst,
Gleich da quollen die Tränen mir.

Und dort blinkte vom Tisch das, schöne Kopfnetz, dein Geschenk,
Köstliches Byssosgeweb, von goldnen Bienlein schwärmend.
Dieses, wenn wir demnächst das blumige Fest
Feiern der herrlichen Tochter Demeters,
Möcht ich <i>ihr</i> weihn, fuer meinen Teil und deinen;
Dass sie hold uns bleibe (denn viel vermag sie),
Dass du zu frueh dir nicht die braune Locke mögest
Fuer Erinna vom lieben Haupte trennen.
</body>
</poem>

<poem id="morike2001102422">
<head>
   <title>An die Geliebte</title>
   <subtitle>1830</subtitle>
   <toctitle>An die Geliebte</toctitle>
   <indextitle>An die Geliebte</indextitle>
   <firstline>Wenn ich, von deinem Anschaun tief gestillt</firstline>
   <keywords>sonnet</keywords>
</head>
<body>
Wenn ich, von deinem Anschaun tief gestillt,
Mich stumm an deinem heilgen Wert vergnüge,
dann hör ich recht die leisen Atemzüge
Des Engels, welcher sich in dir verhüllt.

Und ein erstaunt, ein fragend Lächeln quillt
Auf meinen Mund, ob mich kein Traum betrüge,
Daß nun in dir, zu ewiger Genüge,
Mein kühnster Wunsch, mein einzger, sich erfüllt?

Von Tiefe dann zu Tiefen stürzt mein Sinn,
Ich höre aus der Gottheit nächtger Ferne
Die Quellen des Geschicks melodisch rauschen.

Betäubt kehr ich den Blick nach oben hin,
Zum Himmel auf - da lächeln alle Sterne;
Ich kniee, ihrem Lichtgesang zu lauschen.
</body>
</poem>

<poem id="morike2001102423">
<head>
   <title>Lied vom Winde</title>
   <toctitle>Lied vom Winde</toctitle>
   <indextitle>Lied vom Winde</indextitle>
   <firstline>Sausewind, Brausewind</firstline>
</head>
<body>
Sausewind, Brausewind,
dort und hier!
Deine Heimat sage mir!

,,Kindlein, wir fahren
seit viel vielen Jahren
durch die weit weite Welt,
und möchten's erfragen,
die Antwort erjagen
bei den Bergen, den Meeren,
bei des Himmels klingenden Heeren:
Die wissen es nie.
Bist du klüger als sie,
magst du es sagen. -
Fort, wohlauf!
Halt uns nicht auf!
Kommen andre nach, unsre Brüder,
da frag wieder!''
</body>
</poem>

<poem id="morike2001102424">
<head>
   <title>Septembermorgen</title>
   <toctitle>Septembermorgen</toctitle>
   <indextitle>Septembermorgen</indextitle>
   <firstline>Im Nebel ruhet noch die Welt</firstline>
</head>
<body>
Im Nebel ruhet noch die Welt,
Noch träumen Wald und Wiesen:
Bald siehst du, wenn der Schleier fällt,
Den blauen Himmel unverstellt,
Herbstkräftig die gedämpfte Welt
Im warmen Golde fließen.
</body>
</poem>

<poem id="morike2001102425">
<head>
   <title>Tag und Nacht</title>
   <toctitle>Tag und Nacht</toctitle>
   <indextitle>Tag und Nacht</indextitle>
   <firstline>Schlank und schön ein Mohrenknabe</firstline>
</head>
<body>
Schlank und schön ein Mohrenknabe
Bringt in himmelblauer Schürze
Manche wundersame Gabe,
Kühlen Duft und süße Würze.
    Wenn die Abendlüfte wehen,
    Naht er sachte, kaum gesehen,
    Hat ein Harfenspiel zur Hand.

Auch der Saiten sanftes Tönen
Kann man nächtlich lauschend hören;
Doch scheint alles seiner Schönen,
Ungetreuen, zu gehören;
    Und er wandelt, bis am Haine,
    Bis am See und Wiesenraine
    Er die Spur der Liebsten fand.

Wohl ein Lächeln mag sich leise
Dann ins ernste Antlitz neigen,
Weiße Zähne, glänzend weiße,
Sich wie Sternenlichter zeigen.
    Doch ihn faßt ein reizend Bangen,
    Kommt von ferne Sie gegangen,
    Und er sucht sein dunkles Haus.

Liebchen tritt von Bergeshöhen
In das Tal: da wird es Freude!
Wald und Flur wie neu erstehen
Vor dem Kind im Rosenkleide;
    Alles drängt sich nach der Süßen,
    Alt und jung will sie begrüßen,
    Nur der Knabe bleibet aus.

Und doch ist ein tiefes Ahnen
Von dem Fremdling ihr geblieben;
Wie ein Traum will sie's gemahnen
An ein früh gehegtes Lieben.
    Glänzen dann auf allen Wegen
    Schmuck und Perlen ihr entgegen,
    Denkt sie wohl, wer es gebracht.

Schnell den Schleier vorgezogen,
Steht das Töchterchen in Tränen,
Und der Mutter Friedensbogen
Neigt sich tauend ihrem Sehnen;
    Erd und Himmel haben Frieden,
    Aber ach, sie sind geschieden,
    Sind getrennt wie <i>Tag</i> und <i>Nacht</i>.
</body>
</poem>

<poem id="morike2001102426">
<head>
   <title>Suschens Vogel</title>
   <toctitle>Suschens Vogel</toctitle>
   <indextitle>Suschens Vogel</indextitle>
   <firstline>Ich hatt ein Vöglein, ach wie fein!</firstline>
</head>
<body>
Ich hatt ein Vöglein, ach wie fein!
Kein schöners mag wohl nimmer sein:

Hatt auf der Brust ein Herzlein rot,
Und sung und sung sich schier zu Tod.

Herzvogel mein, du Vogel schön,
Nun sollt du mit zu Markte gehn! -

Und als ich in das Städtlein kam,
Er sass auf meiner Achsel zahm;

Und als ich ging am Haus vorbei
Des Knaben, dem ich brach die Treu,

Der Knab just aus dem Fenster sah,
Mit seinem Finger schnalzt er da:

Wie horchet gleich mein Vogel auf!
Zum Knaben fliegt er husch! hinauf;

Der koset ihn so lieb und hold,
Ich wusst nicht, was ich machen sollt,

Und stund, im Herzen so erschreckt,
Mit Händen mein Gesichte deckt',

Und schlich davon und weinet' sehr,
Ich hört ihn rufen hinterher:

,,Du falsche Maid, behuet dich Gott,
Ich hab doch wieder mein Herzlein rot!''
</body>
</poem>

<poem id="morike2001102427">
<head>
   <title>Abreise</title>
   <toctitle>Abreise</toctitle>
   <indextitle>Abreise</indextitle>
   <firstline>Fertig schon zur Abfahrt steht der Wagen</firstline>
</head>
<body>
Fertig schon zur Abfahrt steht der Wagen,
Und das Posthorn bläst zum letztenmale.
Sagt, wo bleibt der vierte Mann so lange?
Ruft ihn, soll er nicht dahinten bleiben!
- Indes fällt ein rascher Sommerregen;
Eh man hundert zählt, ist er vorueber;
Fast zu kurz, den heissen Staub zu löschen;
Doch auch diese Letzung ist willkommen.
Kuehlung fuellt und Wohlgeruch den weiten
Platz und an den Häusern ringsum öffnet
Sich ein Blumenfenster um das andre.
Endlich kommt der junge Mann. Geschwinde!
Eingestiegen! - Und fort rollt der Wagen.
Aber sehet, auf dem nassen Pflaster
Vor dem Posthaus, wo er stillgehalten,
Lässt er einen trocknen Fleck zuruecke,
Lang und breit, sogar die Räder sieht man
Angezeigt und wo die Pferde standen.
Aber dort in jenem huebschen Hause,
Drin der Juengling sich so lang verweilte,
Steht ein Mädchen hinterm Fensterladen,
Blicket auf die weiss gelassne Stelle,
Hält ihr Tuechlein vors Gesicht und weinet.
Mag es ihr so ernst sein? Ohne Zweifel;
Doch der Jammer wird nicht lange währen:
Mädchenaugen, wisst ihr, trocknen hurtig,
Und eh auf dem Markt die Steine wieder
Alle hell geworden von der Sonne,
Könnet ihr den Wildfang lachen hören.
</body>
</poem>

<poem id="morike2001102428">
<head>
   <title>Die Tochter der Heide</title>
   <toctitle>Die Tochter der Heide</toctitle>
   <indextitle>Die Tochter der Heide</indextitle>
   <firstline>Wasch dich, mein Schwesterchen, wasch dich!</firstline>
</head>
<body>
    Wasch dich, mein Schwesterchen, wasch dich!
Zu Robins Hochzeit gehn wir heut:
Er hat die stolze Ruth gefreit.
    Wir kommen ungebeten;
Wir schmausen nicht, wir tanzen nicht
Und nicht mit lachendem Gesicht
    Komm ich vor ihn zu treten.

    Strähl dich, mein Schwesterchen, strähl dich
Wir wollen ihm singen ein Rätsel-Lied,
Wir wollen ihm klingen ein böses Lied;
    Die Ohren sollen ihm gellen.
Ich will ihr schenken einen Kranz
Von Nesseln und von Dornen ganz.
    Damit fährt sie zur Hölle!

    Schick dich, mein Schwesterchen, schmück dich!
Derweil sie alle sind am Schmaus,
Soll rot in Flammen stehn das Haus,
    Die Gäste schreien und rennen.
Zwei sollen sitzen unverwandt,
Zwei hat ein Sprüchlein festgebannt;
    Zu Kohle müssen sie brennen.

    Lustig, mein Schwesterchen, lustig!
Das war ein alter Ammensang.
Den falschen Rob vergaß ich lang.
    Er soll mich sehen lachen!
Hab ich doch einen andern Schatz,
Der mit mir tanzet auf dem Platz -
    Sie werden Augen machen!
</body>
</poem>

<poem id="morike2001102429">
<head>
   <title>Der Zauberleuchtturm</title>
   <toctitle>Der Zauberleuchtturm</toctitle>
   <indextitle>Der Zauberleuchtturm</indextitle>
   <firstline>Des Zauberers sein Mägdlein saß</firstline>
</head>
<body>
Des Zauberers sein Mägdlein saß
in ihrem Saale rund von Glas;
sie spann beim hellen Kerzenschein
und sang so glockenhell darein.
Der Saal, als eine Kugel klar,
in Lüften aufgehangen war
an einem Turm auf Felsenhöh',
bei Nacht hoch ob der wilden See,
und hing in Sturm und Wettergraus
an einem langen Arm hinaus.
Wenn nun ein Schiff in Nächten schwer
sah weder Rat noch Rettung mehr,
der Lotse zog die Achsel schief,
der Hauptmann alle Teufel rief,
auch der Matrose wollt' verzagen:
O weh mir armen Schwartenmagen!
Auf einmal scheint ein Licht von fern
als wie ein heller Morgenstern;
die Mannschaft jauchzet überlaut:
Heida! jetzt gilt es trockne Haut!
Aus allen Kräften steuert man
jetzt nach dem teuren Licht hinan,
das wächst und wächst und leuchtet fast
wie einer Zaubersonne Glast,
darin ein Mägdlein sitzt und spinnt,
sich beuget ihr Gesang im Wind;
die Männer stehen wie verzückt,
ein jeder nach dem Wunder blickt
und horcht und staunet unverwandt,
dem Steuermann entsinkt die Hand,
hat keiner acht mehr auf das Schiff;
das kracht mit eins am Felsenriff,
die Luft zerreißt ein Jammerschrei:
Herr Gott im Himmel, steh uns bei!
Da löscht die Zauberin ihr Licht;
noch einmal aus der Tiefe bricht
verhallend Weh aus einem Mund;
da zuckt das Schiff und sinkt zu Grund.
</body>
</poem>

<poem id="morike2001102430">
<head>
   <title>Die Geister am Mummelsee</title>
   <toctitle>Die Geister am Mummelsee</toctitle>
   <indextitle>Die Geister am Mummelsee</indextitle>
   <firstline>Vom Berge was kommt dort um Mitternacht spät</firstline>
</head>
<body>
Vom Berge was kommt dort um Mitternacht spät
Mit Fackeln so prächtig herunter?
Ob das wohl zum Tanze, zum Feste noch geht?
Mir klingen die Lieder so munter.
O nein!
So sage, was mag es wohl sein?

Das, was du da siehest, ist Totengeleit,
Und was du da hörest, sind Klagen.
Dem König, dem Zauberer, gilt es zu Leid,
Sie bringen ihn wieder getragen.
O weh!
So sind es die Geister vom See!

Sie schweben herunter ins Mummelseetal -
Sie haben den See schon betreten -
Sie rühren und netzen den Fuss nicht einmal -
Sie schwirren in leisen Gebeten -
O schau,
Am Sarge die glänzende Frau!

Jetzt öffnet der See das grünspiegelnde Tor;
Gib acht, nun tauchen sie nieder!
Es schwankt eine lebende Treppe hervor,
Und - drunten schon summen die Lieder.
Hörst du?
Sie singen ihn unten zur Ruh.

Die Wasser, wie lieblich sie brennen und glühn!
Sie spielen in grünendem Feuer;
Es geisten die Nebel am Ufer dahin,
Zum Meere verzieht sich der Weiher -
Nur still!
Ob dort sich nichts ruehren will?

Es zuckt in der Mitten - o Himmel! ach hilf!
Nun kommen sie wieder, sie kommen!
Es orgelt im Rohr und es klirret im Schilf;
Nur hurtig, die Flucht nur genommen!
Davon!
Sie wittern, sie haschen mich schon!
</body>
</poem>

<poem id="morike2001102431">
<head>
   <title>Frage und Antwort</title>
   <toctitle>Frage und Antwort</toctitle>
   <indextitle>Frage und Antwort</indextitle>
   <firstline>Fragst du mich, woher die bange</firstline>
</head>
<body>
Fragst du mich, woher die bange
Liebe mir zum Herzen kam,
Und warum ich ihr nicht lange
Schon den bittern Stachel nahm?

Sprich, warum mit Geisterschnelle
Wohl der Wind die Fluegel ruehrt,
Und woher die suesse Quelle
Die verborgnen Wasser fuehrt?

Banne du auf seiner Fährte
Mir den Wind in vollem Lauf!
Halte mit der Zaubergerte
Du die suessen Quellen auf!
</body>
</poem>
</workbody>
</kalliopework>
