<?xml version="1.0" encoding="ISO-8859-1"?>

<persons>

<person id="vogelweide" lang="de" type="poet">
  <name>
    <firstname>Walther von der</firstname>
    <lastname>Vogelweide</lastname>
  </name>
  <period>
    <born>
      <date>1170</date>
      <note>ca.</note>
    </born>
    <dead>
      <date>1230</date>
      <note>ca.</note>
    </dead>
  </period>
</person>

<person id="luther" lang="de" type="poet">
  <name>
    <firstname>Martin</firstname>
    <lastname>Luther</lastname>
  </name>
  <period>
    <born>
      <date>1483-11-10</date>
      <place>Eisleben, Sachsen (nu Tyskland)</place>
    </born>
    <dead>
      <date>1546-02-18</date>
      <place>Eisleben, Sachsen (nu Tyskland)</place>
    </dead>
  </period>
</person>

<person id="opitz" lang="de" type="poet">
  <name>
    <firstname>Martin</firstname>
    <lastname>Opitz</lastname>
    <fullname>Martin Opitz von Boberfeld</fullname>
  </name>
  <period>
    <born>
      <date>1597-12-23</date>
      <place>Bunzlau, Schlesien</place>
    </born>
    <dead>
      <date>1639-08-20</date>
      <place>Danzig</place>
    </dead>
  </period>
</person>

<person id="gerhardt" lang="de" type="poet">
  <name>
    <firstname>Paul</firstname>
    <lastname>Gerhardt</lastname>
  </name>
  <period>
    <born>
      <date>1607</date>
      <place>Gräfenhainichen, Sachsen</place>
    </born>
    <dead>
      <date>1676</date>
      <place>Lübben, Spree</place>
    </dead>
  </period>
</person>

<person id="hegedorn" lang="de" type="poet">
  <name>
    <firstname>Friedrich von</firstname>
    <lastname>Hagedorn</lastname>
  </name>
  <period>
    <born>
      <date>1708-04-23</date>
      <place>Hamburg</place>
    </born>
    <dead>
      <date>1754-10-28</date>
      <place>Hamburg</place>
    </dead>
  </period>
</person>

<person id="klopstock" lang="de" type="poet">
  <name>
    <firstname>Friedrich Gottlieb</firstname>
    <lastname>Klopstock</lastname>
  </name>
  <period>
    <born>
      <date>1724-07-02</date>
      <place>Quedlinburg</place>
    </born>
    <dead>
      <date>1803-03-14</date>
      <place>Hamburg</place>
    </dead>
  </period>
</person>

<person id="wieland" lang="de" type="poet">
  <name>
    <firstname>Christoph Martin</firstname>
    <lastname>Wieland</lastname>
  </name>
  <period>
    <born>
      <date>1733-09-05</date>
      <place>Oberholzheim, nær Biberach</place>
    </born>
    <dead>
      <date>1813-01-20</date>
      <place>Weimar</place>
    </dead>
  </period>
</person>

<person id="herder" lang="de" type="poet">
  <name>
    <firstname>Johann Gottfried von</firstname>
    <lastname>Herder</lastname>
  </name>
  <period>
    <born>
      <date>1744-08-25</date>
      <place>Mohrungen (nu Murag, Polen)</place>
    </born>
    <dead>
      <date>1803-12-18</date>
      <place>Weimar</place>
    </dead>
  </period>
</person>

<person id="goethe" lang="de" type="poet">
  <name>
    <firstname>Johann Wolfgang von</firstname>
    <lastname>Goethe</lastname>
  </name>
  <period>
    <born>
      <date>1749-08-28</date>
      <place>Frankfurt am Main</place>
    </born>
    <dead>
      <date>1832-03-22</date>
      <place>Weimar</place>
    </dead>
  </period>
</person>

<person id="schiller" lang="de" type="poet">
  <name>
    <firstname>Friedrich von</firstname>
    <lastname>Schiller</lastname>
    <fullname>Johann Christoph Friedrich von Schiller</fullname>
  </name>
  <period>
    <born>
      <date>1759-11-10</date>
      <place>Marbach, Württemberg</place>
    </born>
    <dead>
      <date>1805-05-09</date>
      <place>Weimar</place>
    </dead>
  </period>
</person>

<person id="hoelderlin" lang="de" type="poet">
  <name>
    <firstname>Friedrich</firstname>
    <lastname>Hölderlin</lastname>
    <fullname>Johann Christian Friedrich Hölderlin</fullname>
  </name>
  <period>
    <born>
      <date>1770-03-20</date>
      <place>Lauffen am Neckar, Württemberg</place>
    </born>
    <dead>
      <date>1843-06-07</date>
      <place>Tübingen</place>
    </dead>
  </period>
</person>

<person id="rueckert" lang="de" type="poet">
  <name>
    <firstname>Friedrich</firstname>
    <lastname>Rückert</lastname>
    <pseudonym>Freimund Raimar</pseudonym>
  </name>
  <period>
    <born>
      <date>1788-05-16</date>
      <place>Schweinfurt</place>
    </born>
    <dead>
      <date>1866-01-31</date>
      <place>Neuses</place>
    </dead>
  </period>
</person>

<person id="heine" lang="de" type="poet">
  <name>
    <firstname>Heinrich</firstname>
    <lastname>Heine</lastname>
  </name>
  <period>
    <born>
      <date>1797-12-13</date>
      <place>Düsseldorf</place>
    </born>
    <dead>
      <date>1856-02-17</date>
      <place>Paris</place>
    </dead>
  </period>
</person>

<person id="lenau" lang="de" type="poet">
  <name>
    <firstname>Nikolaus</firstname>
    <lastname>Lenau</lastname>
    <fullname>Nikolaus Franz Niembsch, Edler von Strehlenau</fullname>
  </name>
  <period>
    <born>
      <date>1802-08-13</date>
      <place>Csatád, Ungarn</place>
    </born>
    <dead>
      <date>1850-08-22</date>
      <place>Oberdöbling nær Wien</place>
    </dead>
  </period>
</person>

<person id="morike" lang="de" type="poet">
  <name>
    <firstname>Eduard</firstname>
    <lastname>Mörike</lastname>
  </name>
  <period>
    <born>
      <date>1804-09-08</date>
      <place>Ludwigsburg</place>
    </born>
    <dead>
      <date>1875-06-04</date>
      <place>Stuttgart</place>
    </dead>
  </period>
</person>

<person id="rilke" lang="de" type="poet">
  <name>
    <firstname>Rainer Maria</firstname>
    <lastname>Rilke</lastname>
  </name>
  <period>
    <born>
      <date>1875-12-04</date>
      <place>Prag, Østrig-Ungarn (nu Tjekkiet)</place>
    </born>
    <dead>
      <date>1926-12-29</date>
      <place>Valmont, Schweiz</place>
    </dead>
  </period>
</person>

<person id="folkeviser" lang="dk" type="collection">
  <name>
    <firstname>Folkeviser</firstname>
  </name>
</person>

<person id="bibel" lang="dk" type="collection">
  <name>
    <firstname>Bibelen</firstname>
  </name>
</person>

<person id="bergenhammer" lang="dk" type="poet">
  <name>
    <firstname>Peder</firstname>
    <lastname>Bergenhammer</lastname>
  </name>
  <period>
    <born>
      <date>1768</date>
    </born>
    <dead>
      <date>1825</date>
    </dead>
  </period>
</person>

<person id="kjaer" lang="dk" type="poet">
  <name>
    <firstname>Søren</firstname>
    <lastname>Kjær</lastname>
  </name>
  <period>
    <born>
      <date>1520</date>
    </born>
    <dead>
      <date>1582</date>
    </dead>
  </period>
</person>

<person id="vedel" lang="dk" type="poet">
  <name>
    <firstname>Anders Sørensen</firstname>
    <lastname>Vedel</lastname>
  </name>
  <period>
    <born>
      <date>1542-11-09</date>
    </born>
    <dead>
      <date>1616-02-13</date>
    </dead>
  </period>
</person>

<person id="sthen" lang="dk" type="poet">
  <name>
    <firstname>Hans Christensen</firstname>
    <lastname>Sthen</lastname>
  </name>
  <period>
    <born>
      <date>1544</date>
    </born>
    <dead>
      <date>1610</date>
    </dead>
  </period>
</person>

<person id="ranch" lang="dk" type="poet">
  <name>
    <firstname>Hieronymus Justesen</firstname>
    <lastname>Ranch</lastname>
  </name>
  <period>
    <born>
      <date>1539</date>
    </born>
    <dead>
      <date>1607-12-03</date>
    </dead>
  </period>
</person>

<person id="hegelund" lang="dk" type="poet">
  <name>
    <firstname>Peder Jensen</firstname>
    <lastname>Hegelund</lastname>
  </name>
  <period>
    <born>
      <date>1542-06-09</date>
    </born>
    <dead>
      <date>1614-02-18</date>
    </dead>
  </period>
</person>

<person id="lyschander" lang="dk" type="poet">
  <name>
    <firstname>Claus Christophersen</firstname>
    <lastname>Lyschander</lastname>
  </name>
  <period>
    <born>
      <date>1558</date>
    </born>
    <dead>
      <date>1624</date>
    </dead>
  </period>
</person>

<person id="terkelsen" lang="dk" type="poet">
  <name>
    <firstname>Søren</firstname>
    <lastname>Terkelsen</lastname>
  </name>
  <period>
    <born>
      <date>?</date>
    </born>
    <dead>
      <date>ca. 1656</date>
    </dead>
  </period>
</person>

<person id="arrebo" lang="dk" type="poet">
  <name>
    <firstname>Anders</firstname>
    <lastname>Arrebo</lastname>
  </name>
  <period>
    <born>
      <date>1587-01-02</date>
    </born>
    <dead>
      <date>1637-03-12</date>
    </dead>
  </period>
</person>

<person id="rothe" lang="dk" type="poet">
  <name>
    <firstname>Tyge</firstname>
    <lastname>Rothe</lastname>
  </name>
  <period>
    <born>
      <date>1731-01-16</date>
    </born>
    <dead>
      <date>1795-12-19</date>
    </dead>
  </period>
</person>
 
<person id="schandrup" lang="dk" type="poet">
  <name>
    <firstname>Jacob Knudsen</firstname>
    <lastname>Schandrup</lastname>
  </name>
  <period>
    <born>
      <date>?</date>
    </born>
    <dead>
      <date>1720</date>
    </dead>
  </period>
</person>

<person id="loenborg" lang="dk" type="poet">
  <name>
    <firstname>Jens Christensen</firstname>
    <lastname>Lønborg</lastname>
  </name>
  <period>
    <born>
      <date>?</date>
    </born>
    <dead>
      <date>1700</date>
    </dead>
  </period>
</person>
 
<person id="wichman" lang="dk" type="poet">
  <name>
    <firstname>Berthel</firstname>
    <lastname>Wichman</lastname>
  </name>
  <period>
    <born>
      <date>1617-02-04</date>
    </born>
    <dead>
      <date>1665-01-10</date>
    </dead>
  </period>
</person>
 
<person id="bording" lang="dk" type="poet">
  <name>
    <firstname>Anders Christensen</firstname>
    <lastname>Bording</lastname>
  </name>
  <period>
    <born>
      <date>1619-01-21</date>
    </born>
    <dead>
      <date>1677-05-24</date>
    </dead>
  </period>
</person>
 
<person id="leonora" lang="dk" type="poet">
  <name>
    <firstname>Leonora Christina</firstname>
    <lastname>Ulfeldt</lastname>
  </name>
  <period>
    <born>
      <date>1621-07-08</date>
    </born>
    <dead>
      <date>1698-03-16</date>
    </dead>
  </period>
</person>

<person id="gerner" lang="dk" type="poet">
  <name>
    <firstname>Henrik</firstname>
    <lastname>Gerner</lastname>
  </name>
  <period>
    <born>
      <date>1629-12-09</date>
    </born>
    <dead>
      <date>1700-05-14</date>
    </dead>
  </period>
</person>
 
<person id="pedersen" lang="dk" type="poet">
  <name>
    <firstname>Poul</firstname>
    <lastname>Pedersen</lastname>
  </name>
  <period>
    <born>
      <date>?</date>
    </born>
    <dead>
      <date>ca. 1700</date>
    </dead>
  </period>
</person>

<person id="syv" lang="dk" type="poet">
  <name>
    <firstname>Peder</firstname>
    <lastname>Syv</lastname>
  </name>
  <period>
    <born>
      <date>1631-02-22</date>
      <place>landsbyen Syv ved Roskilde</place>
    </born>
    <dead>
      <date>1702-02-17</date>
    </dead>
  </period>
</person>
 
<person id="kingo" lang="dk" type="poet">
  <name>
    <firstname>Thomas</firstname>
    <lastname>Kingo</lastname>
  </name>
  <period>
    <born>
      <date>1634-12-15</date>
      <place>Slangerup</place>
    </born>
    <dead>
      <date>1703-10-14</date>
      <place>Odense</place>
    </dead>
  </period>
</person>
 
<person id="engelbretsdatter" lang="dk" type="poet">
  <name>
    <firstname>Dorothe</firstname>
    <lastname>Engelbretsdatter</lastname>
  </name>
  <period>
    <born>
      <date>1634-01-06</date>
    </born>
    <dead>
      <date>1716-02-19</date>
    </dead>
  </period>
</person>

<person id="kok" lang="dk" type="poet">
  <name>
    <firstname>Laurids</firstname>
    <lastname>Kok</lastname>
  </name>
  <period>
    <born>
      <date>1634-09-13</date>
    </born>
    <dead>
      <date>1691-03-17</date>
    </dead>
  </period>
</person>

<person id="sehested" lang="dk" type="poet">
  <name>
    <firstname>Jens Steen</firstname>
    <lastname>Sehested</lastname>
  </name>
  <period>
    <born>
      <date>1640</date>
    </born>
    <dead>
      <date>1698</date>
    </dead>
  </period>
</person>
 
<person id="wormj" lang="dk" type="poet">
  <name>
    <firstname>Jacob</firstname>
    <lastname>Worm</lastname>
  </name>
  <period>
    <born>
      <date>1642-12-8</date>
    </born>
    <dead>
      <date>1692 ca.</date>
    </dead>
  </period>
</person>
 
<person id="wormm" lang="dk" type="poet">
  <name>
    <firstname>Matthias</firstname>
    <lastname>Worm</lastname>
  </name>
  <period>
    <born>
      <date>1636</date>
    </born>
    <dead>
      <date>1707</date>
    </dead>
  </period>
</person>

<person id="lauremberg" lang="dk" type="poet">
  <name>
    <firstname>Hans Willumsen</firstname>
    <lastname>Lauremberg</lastname>
  </name>
  <period>
    <born>
      <date>1590-02-26</date>
    </born>
    <dead>
      <date>1658-02-28</date>
    </dead>
  </period>
</person>
 
<person id="naur" lang="dk" type="poet">
  <name>
    <firstname>Elias Eskildsen</firstname>
    <lastname>Naur</lastname>
  </name>
  <period>
    <born>
      <date>1650-02-17</date>
    </born>
    <dead>
      <date>1728-05-06</date>
    </dead>
  </period>
</person>
 
<person id="helt" lang="dk" type="poet">
  <name>
    <firstname>Vilhelm</firstname>
    <lastname>Helt</lastname>
  </name>
  <period>
    <born>
      <date>1652-05-19</date>
    </born>
    <dead>
      <date>1724-01-16</date>
    </dead>
  </period>
</person>

<person id="reenberg" lang="dk" type="poet">
  <name>
    <firstname>Tøger</firstname>
    <lastname>Reenberg</lastname>
  </name>
  <period>
    <born>
      <date>1656-10-10</date>
    </born>
    <dead>
      <date>1742-06-24</date>
    </dead>
  </period>
</person>
 
<person id="sorterup" lang="dk" type="poet">
  <name>
    <firstname>Jørgen Jørgensen</firstname>
    <lastname>Sorterup</lastname>
  </name>
  <period>
    <born>
      <date>1662-11-01</date>
    </born>
    <dead>
      <date>1723-10-04</date>
    </dead>
  </period>
</person>

<person id="holberg" lang="dk" type="poet">
  <name>
    <firstname>Ludvig</firstname>
    <lastname>Holberg</lastname>
  </name>
  <period>
    <born>
      <date>1684-12-03</date>
      <place>Bergen</place>
    </born>
    <dead>
      <date>1754-01-28</date>
      <place>København</place>
    </dead>
  </period>
</person>

<person id="falster" lang="dk" type="poet">
  <name>
    <firstname>Christian</firstname>
    <lastname>Falster</lastname>
  </name>
  <period>
    <born>
      <date>1690-01-01</date>
    </born>
    <dead>
      <date>1752-10-24</date>
    </dead>
  </period>
</person>

<person id="brorson" lang="dk" type="poet">
  <name>
    <firstname>H. A.</firstname>
    <lastname>Brorson</lastname>
    <fullname>Hans Adolph Brorson</fullname>
  </name>
  <period>
    <born>
      <date>1694-06-20</date>
      <place>Randerup</place>
    </born>
    <dead>
      <date>1764-06-03</date>
      <place>Ribe</place>
    </dead>
  </period>
</person>
 
<person id="stub" lang="dk" type="poet">
  <name>
    <firstname>Ambrosius</firstname>
    <lastname>Stub</lastname>
  </name>
  <period>
    <born>
      <date>1705-05-17</date>
    </born>
    <dead>
      <date>1758-07-15</date>
    </dead>
  </period>
</person>
 
<person id="wadskiaer" lang="dk" type="poet">
  <name>
    <firstname>Christian Frederik</firstname>
    <lastname>Wadskiær</lastname>
  </name>
  <period>
    <born>
      <date>1713</date>
    </born>
    <dead>
      <date>1779</date>
    </dead>
  </period>
</person>
 
<person id="stenersen" lang="dk" type="poet">
  <name>
    <firstname>P. C.</firstname>
    <lastname>Stenersen</lastname>
    <fullname>Peter Christopher Stenersen</fullname>
  </name>
  <period>
    <born>
      <date>1723-04-09</date>
    </born>
    <dead>
      <date>1776-04-17</date>
    </dead>
  </period>
</person>
 
<person id="biehl" lang="dk" type="poet">
  <name>
    <firstname>Charlotte Dorothea</firstname>
    <lastname>Biehl</lastname>
  </name>
  <period>
    <born>
      <date>1731-06-02</date>
    </born>
    <dead>
      <date>1788-05-17</date>
    </dead>
  </period>
</person>
 
<person id="tode" lang="dk" type="poet">
  <name>
    <firstname>Johann Clemens</firstname>
    <lastname>Tode</lastname>
  </name>
  <period>
    <born>
      <date>1736-06-24</date>
    </born>
    <dead>
      <date>1806-03-16</date>
    </dead>
  </period>
</person>
 
<person id="wandal" lang="dk" type="poet">
  <name>
    <firstname>Peder Topp</firstname>
    <lastname>Wandall</lastname>
  </name>
  <period>
    <born>
      <date>1737-12-25</date>
    </born>
    <dead>
      <date>1794-10-05</date>
    </dead>
  </period>
</person>

<person id="hertzb" lang="dk" type="poet">
  <name>
    <firstname>Birgitte</firstname>
    <lastname>Boye</lastname>
  </name>
  <period>
    <born>
      <date>1742-03-07</date>
    </born>
    <dead>
      <date>1824-10-17</date>
    </dead>
  </period>
</person>
 
<person id="wessel" lang="dk" type="poet">
  <name>
    <firstname>Johan Herman</firstname>
    <lastname>Wessel</lastname>
  </name>
  <period>
    <born>
      <date>1742-10-06</date>
      <place>Jonsrud, nær Vestby, Norge</place>
    </born>
    <dead>
      <date>1785-12-29</date>
      <place>København</place>
    </dead>
  </period>
</person>
 
<person id="ewald" lang="dk" type="poet">
  <name>
    <firstname>Johannes</firstname>
    <lastname>Ewald</lastname>
  </name>
  <period>
    <born>
      <date>1743-11-18</date>
      <place>København</place>
    </born>
    <dead>
      <date>1781-03-17</date>
      <place>København</place>
    </dead>
  </period>
</person>

<person id="trojelpm" lang="dk" type="poet">
  <name>
    <firstname>Peder Magnus</firstname>
    <lastname>Trojel</lastname>
  </name>
  <period>
    <born>
      <date>1743-6-3</date>
      <note>eller 1743-6-6</note>
    </born>
    <dead>
      <date>1793-12-16</date>
    </dead>
  </period>
</person>

<person id="schoenheyder" lang="dk" type="poet">
  <name>
    <firstname>Johan Heinrich</firstname>
    <lastname>Schønheyder</lastname>
  </name>
  <period>
    <born>
      <date>1744-06-07</date>
    </born>
    <dead>
      <date>1831-05-25</date>
    </dead>
  </period>
</person>
 
<person id="stockfleth" lang="dk" type="poet">
  <name>
    <firstname>Th.</firstname>
    <lastname>Stockfleth</lastname>
  </name>
  <period>
    <born>
      <date>1743</date>
    </born>
    <dead>
      <date>1808</date>
    </dead>
  </period>
</person>
 
<person id="abrahamson" lang="dk" type="poet">
  <name>
    <firstname>W. H. F.</firstname>
    <lastname>Abrahamson</lastname>
    <fullname>Werner H. F. Abrahamson</fullname>
  </name>
  <period>
    <born>
      <date>1744-04-10</date>
    </born>
    <dead>
      <date>1812-09-22</date>
    </dead>
  </period>
</person>
 
<person id="thaarup" lang="dk" type="poet">
  <name>
    <firstname>Thomas</firstname>
    <lastname>Thaarup</lastname>
  </name>
  <period>
    <born>
      <date>1749-08-21</date>
    </born>
    <dead>
      <date>1821-07-12</date>
    </dead>
  </period>
</person>
 
<person id="bruuntc" lang="dk" type="poet">
  <name>
    <firstname>Thomas Christopher</firstname>
    <lastname>Bruun</lastname>
  </name>
  <period>
    <born>
      <date>1750-11-02</date>
      <place>Gaunø, Sjælland</place>
    </born>
    <dead>
      <date>1834-06-24</date>
    </dead>
  </period>
</person>
 
<person id="brun" lang="dk" type="poet">
  <name>
    <firstname>Johan Nordahl</firstname>
    <lastname>Brun</lastname>
  </name>
  <period>
    <born>
      <date>1745-03-21</date>
    </born>
    <dead>
      <date>1816-07-26</date>
    </dead>
  </period>
</person>

<person id="obelitz" lang="dk" type="poet">
  <name>
    <firstname>Ove von</firstname>
    <lastname>Obelitz</lastname>
  </name>
  <period>
    <born>
      <date>1750</date>
    </born>
    <dead>
      <date>1804</date>
    </dead>
  </period>
</person>

<person id="thoroup" lang="dk" type="poet">
  <name>
    <firstname>Adam Gottlob</firstname>
    <lastname>Thoroup</lastname>
  </name>
  <period>
    <born>
      <date>1751</date>
    </born>
    <dead>
      <date>1804</date>
    </dead>
  </period>
</person>

<person id="colbjoernsen" lang="dk" type="poet">
  <name>
    <firstname>Edvard</firstname>
    <lastname>Colbjørnsen</lastname>
  </name>
  <period>
    <born>
      <date>1751</date>
    </born>
    <dead>
      <date>1792</date>
    </dead>
  </period>
</person>
 
<person id="trojel" lang="dk" type="poet">
  <name>
    <firstname>Peder Kofod</firstname>
    <lastname>Trojel</lastname>
  </name>
  <period>
    <born>
      <date>1754-05-05</date>
    </born>
    <dead>
      <date>1784-11-09</date>
    </dead>
  </period>
</person>

<person id="falsen" lang="dk" type="poet">
  <name>
    <firstname>Enevold de</firstname>
    <lastname>Falsen</lastname>
  </name>
  <period>
    <born>
      <date>1755-10-17</date>
    </born>
    <dead>
      <date>1808-11-16</date>
    </dead>
  </period>
</person>

<person id="pram" lang="dk" type="poet">
  <name>
    <firstname>Christen H.</firstname>
    <lastname>Pram</lastname>
    <fullname>Christen Henriksen Pram</fullname>
  </name>
  <period>
    <born>
      <date>1756-09-04</date>
    </born>
    <dead>
      <date>1821-11-25</date>
    </dead>
  </period>
</person>
 
<person id="sander" lang="dk" type="poet">
  <name>
    <firstname>L. C.</firstname>
    <lastname>Sander</lastname>
    <fullname>Levin Christian Sander</fullname>
  </name>
  <period>
    <born>
      <date>1756-11-13</date>
    </born>
    <dead>
      <date>1819-07-29</date>
    </dead>
  </period>
</person>

<person id="heibergpa" lang="dk" type="poet">
  <name>
    <firstname>P. A.</firstname>
    <lastname>Heiberg</lastname>
    <fullname>Peter Andreas Heiberg</fullname>
  </name>
  <period>
    <born>
      <date>1758-11-16</date>
      <place>Vordingborg</place>
    </born>
    <dead>
      <date>1841-04-30</date>
      <place>Paris</place>
    </dead>
  </period>
</person>
 
<person id="rahbek" lang="dk" type="poet">
  <name>
    <firstname>Knud Lyne</firstname>
    <lastname>Rahbek</lastname>
  </name>
  <period>
    <born>
      <date>1760-12-18</date>
    </born>
    <dead>
      <date>1830-04-22</date>
    </dead>
  </period>
</person>
 
<person id="riber" lang="dk" type="poet">
  <name>
    <firstname>Hans Vilhelm</firstname>
    <lastname>Riber</lastname>
  </name>
  <period>
    <born>
      <date>1760-01-07</date>
    </born>
    <dead>
      <date>1796-11-26</date>
    </dead>
  </period>
</person>

<person id="baggesen" lang="dk" type="poet">
  <name>
    <firstname>Jens</firstname>
    <lastname>Baggesen</lastname>
    <fullname>Jens Immanuel Baggesen</fullname>
  </name>
  <period>
    <born>
      <date>1764-02-15</date>
      <place>Korsør</place>
    </born>
    <dead>
      <date>1826-10-03</date>
      <place>Hamburg</place>
    </dead>
  </period>
</person>
 
<person id="olufsen" lang="dk" type="poet">
  <name>
    <firstname>Oluf Christian</firstname>
    <lastname>Olufsen</lastname>
  </name>
  <period>
    <born>
      <date>1764-01-20</date>
    </born>
    <dead>
      <date>1827-05-19</date>
    </dead>
  </period>
</person>

<person id="haste" lang="dk" type="poet">
  <name>
    <firstname>Peder Horrebow</firstname>
    <lastname>Haste</lastname>
  </name>
  <period>
    <born>
      <date>1765-01-12</date>
    </born>
    <dead>
      <date>1831-01-28</date>
    </dead>
  </period>
</person>

<person id="frankenau" lang="dk" type="poet">
  <name>
    <firstname>Rasmus</firstname>
    <lastname>Frankenau</lastname>
  </name>
  <period>
    <born>
      <date>1767-01-06</date>
    </born>
    <dead>
      <date>1814-10-12</date>
    </dead>
  </period>
</person>

<person id="staffeldt" lang="dk" type="poet">
  <name>
    <firstname> A.W. Schack von</firstname>
    <lastname>Staffeldt</lastname>
  </name>
  <period>
    <born>
      <date>1769-03-28</date>
    </born>
    <dead>
      <date>1826-12-26</date>
    </dead>
  </period>
</person>
 
<person id="horrebow" lang="dk" type="poet">
  <name>
    <firstname>Otto</firstname>
    <lastname>Horrebow</lastname>
  </name>
  <period>
    <born>
      <date>1769</date>
    </born>
    <dead>
      <date>1823</date>
    </dead>
  </period>
</person>

<person id="hoeghguldbergf" lang="dk" type="poet">
  <name>
    <firstname>Frederik</firstname>
    <lastname>Høegh-Guldberg</lastname>
  </name>
  <period>
    <born>
      <date>1771-03-26</date>
    </born>
    <dead>
      <date>1852-09-21</date>
    </dead>
  </period>
</person>

<person id="bruunmc" lang="dk" type="poet">
  <name>
    <firstname>Malthe Conrad</firstname>
    <lastname>Bruun</lastname>
  </name>
  <period>
    <born>
      <date>1775-08-12</date>
    </born>
    <dead>
      <date>1826-12-14</date>
    </dead>
  </period>
</person>
 
<person id="soeborg" lang="dk" type="poet">
  <name>
    <firstname>Carl</firstname>
    <lastname>Søeborg</lastname>
  </name>
  <period>
    <born>
      <date>1775-08-15</date>
    </born>
    <dead>
      <date>1852-11-03</date>
    </dead>
  </period>
</person>

<person id="hempel" lang="dk" type="poet">
  <name>
    <firstname>Søren</firstname>
    <lastname>Hempel</lastname>
  </name>
  <period>
    <born>
      <date>1775</date>
    </born>
    <dead>
      <date>1844</date>
    </dead>
  </period>
</person>

<person id="foersom" lang="dk" type="poet">
  <name>
    <firstname>Peter</firstname>
    <lastname>Foersom</lastname>
  </name>
  <period>
    <born>
      <date>1777-02-20</date>
    </born>
    <dead>
      <date>1817-01-24</date>
    </dead>
  </period>
</person>

<person id="bruunnt" lang="dk" type="poet">
  <name>
    <firstname>N. T.</firstname>
    <lastname>Bruun</lastname>
  </name>
  <period>
    <born>
      <date>1778-01-19</date>
    </born>
    <dead>
      <date>1823-06-08</date>
    </dead>
  </period>
</person>

<person id="oehlenschlaeger" lang="dk" type="poet">
  <name>
    <firstname>Adam</firstname>
    <lastname>Oehlenschläger</lastname>
  </name>
  <period>
    <born>
      <date>1779-11-14</date>
    </born>
    <dead>
      <date>1850-01-20</date>
    </dead>
  </period>
</person>
 
<person id="magnusson" lang="dk" type="poet">
  <name>
    <firstname>Finnur</firstname>
    <lastname>Magnusson</lastname>
  </name>
  <period>
    <born>
      <date>1781</date>
    </born>
    <dead>
      <date>1847</date>
    </dead>
  </period>
</person>

<person id="blicher" lang="dk" type="poet">
  <name>
    <firstname>Steen Steensen</firstname>
    <lastname>Blicher</lastname>
  </name>
  <period>
    <born>
      <date>1782-10-11</date>
      <place>Vium, Jylland</place>
    </born>
    <dead>
      <date>1848-03-26</date>
      <place>Spentrup, Jylland</place>
    </dead>
  </period>
</person>
 
<person id="grundtvig" lang="dk" type="poet">
  <name>
    <firstname>N. F. S.</firstname>
    <lastname>Grundtvig</lastname>
    <fullname>Nikolai Frederik Severin Grundtvig</fullname>
  </name>
  <period>
    <born>
      <date>1783-09-08</date>
      <place>Udby</place>
    </born>
    <dead>
      <date>1872-09-02</date>
      <place>København</place>
    </dead>
  </period>
</person>
 
<person id="bredahl" lang="dk" type="poet">
  <name>
    <firstname>Christian Hviid</firstname>
    <lastname>Bredahl</lastname>
  </name>
  <period>
    <born>
      <date>1784-10-03</date>
    </born>
    <dead>
      <date>1860-01-16</date>
    </dead>
  </period>
</person>
 
<person id="ingemann" lang="dk" type="poet">
  <name>
    <firstname>B. S.</firstname>
    <lastname>Ingemann</lastname>
    <fullname>Bernhard Severin Ingemann</fullname>
  </name>
  <period>
    <born>
      <date>1789-05-28</date>
      <place>Torkilstrup</place>
    </born>
    <dead>
      <date>1862-02-24</date>
      <place>Sorø</place>
    </dead>
  </period>
</person>
 
<person id="hauch" lang="dk" type="poet">
  <name>
    <firstname>Carsten</firstname>
    <lastname>Hauch</lastname>
  </name>
  <period>
    <born>
      <date>1790-05-12</date>
    </born>
    <dead>
      <date>1872-03-04</date>
    </dead>
  </period>
</person>
 
<person id="dampe" lang="dk" type="poet">
  <name>
    <firstname>Jacob J.</firstname>
    <lastname>Dampe</lastname>
    <fullname>Jacob Jacobsen Dampe</fullname>
  </name>
  <period>
    <born>
      <date>1790-01-17</date>
    </born>
    <dead>
      <date>1867</date>
    </dead>
  </period>
</person>

<person id="irgens" lang="dk" type="poet">
  <name>
    <firstname>Hanna</firstname>
    <lastname>Irgens</lastname>
  </name>
  <period>
    <born>
      <date>1792-08-19</date>
      <place>Kbh.</place>
    </born>
    <dead>
      <date>1853-06-13</date>
    </dead>
  </period>
</person>
 
<person id="heibergjl" lang="dk" type="poet">
  <name>
    <firstname>Johan Ludvig</firstname>
    <lastname>Heiberg</lastname>
  </name>
  <period>
    <born>
      <date>1791-12-14</date>
      <place>København</place>
    </born>
    <dead>
      <date>1860-08-25</date>
      <place>Bonderup</place>
    </dead>
  </period>
</person>
 
<person id="boedtcher" lang="dk" type="poet">
  <name>
    <firstname>Ludvig</firstname>
    <lastname>Bødtcher</lastname>
  </name>
  <period>
    <born>
      <date>1793-04-22</date>
    </born>
    <dead>
      <date>1874-10-01</date>
    </dead>
  </period>
</person>
 
<person id="moellerpm" lang="dk" type="poet">
  <name>
    <firstname>Poul Martin</firstname>
    <lastname>Møller</lastname>
  </name>
  <period>
    <born>
      <date>1794-03-21</date>
    </born>
    <dead>
      <date>1838-03-12</date>
    </dead>
  </period>
</person>
 
<person id="winter" lang="dk" type="poet">
  <name>
    <firstname>Christian</firstname>
    <lastname>Winther</lastname>
  </name>
  <period>
    <born>
      <date>1796-07-29</date>
    </born>
    <dead>
      <date>1876-12-30</date>
    </dead>
  </period>
</person>
 
<person id="wilster" lang="dk" type="poet">
  <name>
    <firstname>Christian</firstname>
    <lastname>Wilster</lastname>
  </name>
  <period>
    <born>
      <date>1797-09-27</date>
    </born>
    <dead>
      <date>1840-01-11</date>
    </dead>
  </period>
</person>
 
<person id="hertzh" lang="dk" type="poet">
  <name>
    <firstname>Henrik</firstname>
    <lastname>Hertz</lastname>
  </name>
  <period>
    <born>
      <date>1797/98-08-25</date>
    </born>
    <dead>
      <date>1870-02-25</date>
    </dead>
  </period>
</person>
 
<person id="liunge" lang="dk" type="poet">
  <name>
    <firstname>Andreas Peter</firstname>
    <lastname>Liunge</lastname>
  </name>
  <period>
    <born>
      <date>1798</date>
    </born>
    <dead>
      <date>1879</date>
    </dead>
  </period>
</person>

<person id="krossing" lang="dk" type="poet">
  <name>
    <firstname>Nikolaj</firstname>
    <lastname>Krossing</lastname>
  </name>
  <period>
    <born>
      <date>1798-06-13</date>
    </born>
    <dead>
      <date>1872-02-05</date>
    </dead>
  </period>
</person>

<person id="overskou" lang="dk" type="poet">
  <name>
    <firstname>Thomas</firstname>
    <lastname>Overskou</lastname>
  </name>
  <period>
    <born>
      <date>1798-10-11</date>
    </born>
    <dead>
      <date>1873-11-07</date>
    </dead>
  </period>
</person>
 
<person id="aarestrup" lang="dk" type="poet">
  <name>
    <firstname>Emil</firstname>
    <lastname>Aarestrup</lastname>
  </name>
  <period>
    <born>
      <date>1800-12-04</date>
    </born>
    <dead>
      <date>1856-07-21</date>
    </dead>
  </period>
</person>
 
<person id="deichmann" lang="dk" type="poet">
  <name>
    <firstname>Christian</firstname>
    <lastname>Deichmann</lastname>
  </name>
  <period>
    <born>
      <date>1800-10-11</date>
    </born>
    <dead>
      <date>1838-08-09</date>
    </dead>
  </period>
</person>

<person id="andersen" lang="dk" type="poet">
  <name>
    <firstname>H. C.</firstname>
    <lastname>Andersen</lastname>
    <fullname>Hans Christian Andersen</fullname>
  </name>
  <period>
    <born>
      <date>1805-04-02</date>
      <place>Odense</place>
    </born>
    <dead>
      <date>1875-08-04</date>
      <place>København</place>
    </dead>
  </period>
</person>
 
<person id="bagger" lang="dk" type="poet">
  <name>
    <firstname>Carl</firstname>
    <lastname>Bagger</lastname>
  </name>
  <period>
    <born>
      <date>1807-05-11</date>
    </born>
    <dead>
      <date>1846-10-25</date>
    </dead>
  </period>
</person>
 
<person id="mueller" lang="dk" type="poet">
  <name>
    <firstname>Frederik</firstname>
    <lastname>Paludan-Müller</lastname>
  </name>
  <period>
    <born>
      <date>1809-02-07</date>
    </born>
    <dead>
      <date>1876-12-28</date>
    </dead>
  </period>
</person>

<person id="karstensen" lang="dk" type="poet">
  <name>
    <firstname>Kristen</firstname>
    <lastname>Karstensen</lastname>
  </name>
  <period>
    <born>
      <date>1809</date>
    </born>
    <dead>
      <date>1882</date>
    </dead>
  </period>
</person>

<person id="faber" lang="dk" type="poet">
  <name>
    <firstname>Peter</firstname>
    <lastname>Faber</lastname>
  </name>
  <period>
    <born>
      <date>1810-10-07</date>
    </born>
    <dead>
      <date>1877-04-25</date>
    </dead>
  </period>
</person>
 
<person id="gerson" lang="dk" type="poet">
  <name>
    <firstname>Julius Christian</firstname>
    <lastname>Gerson</lastname>
  </name>
  <period>
    <born>
      <date>1811-11-15</date>
    </born>
    <dead>
      <date>1894-02-28</date>
    </dead>
  </period>
</person>
 
<person id="holst" lang="dk" type="poet">
  <name>
    <firstname>H. P.</firstname>
    <lastname>Holst</lastname>
    <fullname>Hans Peter Holst</fullname>
  </name>
  <period>
    <born>
      <date>1811-10-23</date>
      <note>eller 1811-10-22</note>
    </born>
    <dead>
      <date>1893-06-02</date>
    </dead>
  </period>
</person>

<person id="plough" lang="dk" type="poet">
  <name>
    <firstname>Carl</firstname>
    <lastname>Ploug</lastname>
  </name>
  <period>
    <born>
      <date>1813-10-29</date>
    </born>
    <dead>
      <date>1894-10-27</date>
    </dead>
  </period>
</person>
 
<person id="moellerpl" lang="dk" type="poet">
  <name>
    <firstname>P. L.</firstname>
    <lastname>Møller</lastname>
  </name>
  <period>
    <born>
      <date>1814-04-18</date>
    </born>
    <dead>
      <date>1865-12-06</date>
    </dead>
  </period>
</person>
 
<person id="lembcke" lang="dk" type="poet">
  <name>
    <firstname>Edvard</firstname>
    <lastname>Lembcke</lastname>
  </name>
  <period>
    <born>
      <date>1815-06-15</date>
    </born>
    <dead>
      <date>1897-03-21</date>
    </dead>
  </period>
</person>

<person id="hostrup" lang="dk" type="poet">
  <name>
    <firstname>Jens Christian</firstname>
    <lastname>Hostrup</lastname>
    <pseudonym>Jens Kristrup</pseudonym>
  </name>
  <period>
    <born>
      <date>1818-05-20</date>
    </born>
    <dead>
      <date>1892-11-21</date>
    </dead>
  </period>
</person>
 
<person id="kaalund" lang="dk" type="poet">
  <name>
    <firstname>Hans Vilhelm</firstname>
    <lastname>Kaalund</lastname>
  </name>
  <period>
    <born>
      <date>1818-06-23</date>
    </born>
    <dead>
      <date>1885-04-27</date>
    </dead>
  </period>
</person>

<person id="recke" lang="dk" type="poet">
  <name>
    <firstname>Adolph</firstname>
    <lastname>Recke</lastname>
  </name>
  <period>
    <born>
      <date>1820-05-17</date>
    </born>
    <dead>
      <date>1867-12-06</date>
    </dead>
  </period>
</person>
 
<person id="molbech" lang="dk" type="poet">
  <name>
    <firstname>Chr. K. F.</firstname>
    <lastname>Molbech</lastname>
  </name>
  <period>
    <born>
      <date>1821-07-20</date>
    </born>
    <dead>
      <date>1888-05-20</date>
    </dead>
  </period>
</person>

<person id="boegh" lang="dk" type="poet">
  <name>
    <firstname>Erik</firstname>
    <lastname>Bøgh</lastname>
  </name>
  <period>
    <born>
      <date>1822-01-17</date>
    </born>
    <dead>
      <date>1899-08-17</date>
    </dead>
  </period>
</person>

<person id="helms" lang="dk" type="poet">
  <name>
    <firstname>Johannes</firstname>
    <lastname>Helms</lastname>
  </name>
  <period>
    <born>
      <date>1828-11-08</date>
    </born>
    <dead>
      <date>1895-12-04</date>
    </dead>
  </period>
</person>

<person id="richardt" lang="dk" type="poet">
  <name>
    <firstname>Christian</firstname>
    <lastname>Richardt</lastname>
  </name>
  <period>
    <born>
      <date>1831-05-25</date>
    </born>
    <dead>
      <date>1892-12-18</date>
    </dead>
  </period>
</person>
 
<person id="bergsoe" lang="dk" type="poet">
  <name>
    <firstname>Vilhelm</firstname>
    <lastname>Bergsøe</lastname>
  </name>
  <period>
    <born>
      <date>1835-02-08</date>
    </born>
    <dead>
      <date>1911-06-26</date>
    </dead>
  </period>
</person>

<person id="schandorph" lang="dk" type="poet">
  <name>
    <firstname>Sophus</firstname>
    <lastname>Schandorph</lastname>
  </name>
  <period>
    <born>
      <date>1836-05-08</date>
    </born>
    <dead>
      <date>1901-01-01</date>
    </dead>
  </period>
</person>

<person id="schmidt" lang="dk" type="poet">
  <name>
    <firstname>Rudolf</firstname>
    <lastname>Schmidt</lastname>
  </name>
  <period>
    <born>
      <date>1836-07-25</date>
    </born>
    <dead>
      <date>1899-04-05</date>
    </dead>
  </period>
</person>

<person id="brandes" lang="dk" type="poet">
  <name>
    <firstname>Georg</firstname>
    <lastname>Brandes</lastname>
  </name>
  <period>
    <born>
      <date>1842-02-04</date>
    </born>
    <dead>
      <date>1927-02-19</date>
    </dead>
  </period>
</person>

<person id="nielsenz" lang="dk" type="poet">
  <name>
    <firstname>Zakarias</firstname>
    <lastname>Nielsen</lastname>
    <note>Døbt Zacarias</note>
  </name>
  <period>
    <born>
      <date>1844-06-05</date>
    </born>
    <dead>
      <date>1922-11-11</date>
    </dead>
  </period>
</person>

<person id="drachmann" lang="dk" type="poet">
  <name>
    <firstname>Holger</firstname>
    <lastname>Drachmann</lastname>
  </name>
  <period>
    <born>
      <date>1846-10-09</date>
    </born>
    <dead>
      <date>1908-01-14</date>
    </dead>
  </period>
</person>
 
<person id="jacobsen" lang="dk" type="poet">
  <name>
    <firstname>J. P.</firstname>
    <lastname>Jacobsen</lastname>
  </name>
  <period>
    <born>
      <date>1847-04-07</date>
      <place>Thisted</place>
    </born>
    <dead>
      <date>1885-04-30</date>
      <place>Thisted</place>
    </dead>
  </period>
</person>

<person id="gjellerup" lang="dk" type="poet">
  <name>
    <firstname>Karl</firstname>
    <lastname>Gjellerup</lastname>
  </name>
  <period>
    <born>
      <date>1857-06-02</date>
    </born>
    <dead>
      <date>1919-10-11</date>
    </dead>
  </period>
</person>

<person id="bang" lang="dk" type="poet">
  <name>
    <firstname>Herman</firstname>
    <lastname>Bang</lastname>
  </name>
  <period>
    <born>
      <date>1857-04-20</date>
    </born>
    <dead>
      <date>1912-01-29</date>
    </dead>
  </period>
</person>
 
<person id="knudsen" lang="dk" type="poet">
  <name>
    <firstname>Jakob</firstname>
    <lastname>Knudsen</lastname>
  </name>
  <period>
    <born>
      <date>1858-09-14</date>
    </born>
    <dead>
      <date>1917-01-21</date>
    </dead>
  </period>
</person>
 
<person id="esmann" lang="dk" type="poet">
  <name>
    <firstname>Gustav</firstname>
    <lastname>Esmann</lastname>
  </name>
  <period>
    <born>
      <date>1860-08-17</date>
    </born>
    <dead>
      <date>1904-09-04</date>
      <note>Skudt af elskerinde</note>
    </dead>
  </period>
</person>
 
<person id="nansen" lang="dk" type="poet">
  <name>
    <firstname>Peter</firstname>
    <lastname>Nansen</lastname>
  </name>
  <period>
    <born>
      <date>1861-01-20</date>
    </born>
    <dead>
      <date>1918-07-31</date>
    </dead>
  </period>
</person>
 
<person id="stuckenberg" lang="dk" type="poet">
  <name>
    <firstname>Viggo</firstname>
    <lastname>Stuckenberg</lastname>
  </name>
  <period>
    <born>
      <date>1863-09-17</date>
    </born>
    <dead>
      <date>1905-12-06</date>
    </dead>
  </period>
</person>
 
<person id="claussen" lang="dk" type="poet">
  <name>
    <firstname>Sophus</firstname>
    <lastname>Claussen</lastname>
  </name>
  <period>
    <born>
      <date>1865-09-12</date>
    </born>
    <dead>
      <date>1931-04-11</date>
    </dead>
  </period>
</person>

<person id="michaelis" lang="dk" type="poet">
  <name>
    <firstname>Sophus</firstname>
    <lastname>Michaëlis</lastname>
  </name>
  <period>
    <born>
      <date>1865-05-14</date>
    </born>
    <dead>
      <date>1932-01-28</date>
    </dead>
  </period>
</person>

<person id="aakjaer" lang="dk" type="poet">
  <name>
    <firstname>Jeppe</firstname>
    <lastname>Aakjær</lastname>
  </name>
  <period>
    <born>
      <date>1866-09-10</date>
      <place>Aakjær, Fly Sogn</place>
    </born>
    <dead>
      <date>1930-04-22</date>
      <place>Jenle, Grinderslev Sogn</place>
    </dead>
  </period>
</person>

<person id="mylius" lang="dk" type="poet">
  <name>
    <firstname>Ludvig</firstname>
    <lastname>Mylius-Erichsen</lastname>
  </name>
  <period>
    <born>
      <date>1872-01-15</date>
    </born>
    <dead>
      <date>1907-11-25</date>
    </dead>
  </period>
</person>

<person id="larsent" lang="dk" type="poet">
  <name>
    <firstname>Thøger</firstname>
    <lastname>Larsen</lastname>
  </name>
  <period>
    <born>
      <date>1875-04-05</date>
    </born>
    <dead>
      <date>1928-05-29</date>
    </dead>
  </period>
</person>

<person id="kidde" lang="dk" type="poet">
  <name>
    <firstname>Harald</firstname>
    <lastname>Kidde</lastname>
  </name>
  <period>
    <born>
      <date>1878-08-14</date>
    </born>
    <dead>
      <date>1918-11-23</date>
    </dead>
  </period>
</person>

<person id="villon" lang="fr" type="poet">
  <name>
    <firstname>François</firstname>
    <lastname>Villon</lastname>
    <realname>François De Montcorbier</realname>
    <realname>François Des Loges</realname>
  </name>
  <period>
    <born>
      <date>1431</date>
      <place>Paris</place>
    </born>
    <dead>
      <date>1485</date>
    </dead>
  </period>
</person>

<person id="marot" lang="fr" type="poet">
  <name>
    <firstname>Clément</firstname>
    <lastname>Marot</lastname>
  </name>
  <period>
    <born>
      <date>1496-11-23</date>
      <place>Cahors, Frankrig</place>
    </born>
    <dead>
      <date>1544-09-10</date>
      <place>Turino, Savoy (nu Italien)</place>
    </dead>
  </period>
</person>

<person id="urfe" lang="fr" type="poet">
  <name>
    <firstname>Honoré</firstname>
    <lastname>d'Urfé</lastname>
  </name>
  <period>
    <born>
      <date>1567-02-10</date>
      <place>Marseille</place><note>måske 1567-02-11</note>
    </born>
    <dead>
      <date>1625-06-01</date>
      <place>Villefranche-sur-Mer, Frankrig</place>
    </dead>
  </period>
</person>

<person id="corneille" lang="fr" type="poet">
  <name>
    <firstname>Pierre</firstname>
    <lastname>Corneille</lastname>
  </name>
  <period>
    <born>
      <date>1606-06-06</date>
      <place>Rouen, Frankrig</place>
    </born>
    <dead>
      <date>1684-10-01</date>
      <place>Paris</place>
    </dead>
  </period>
</person>

<person id="fontaine" lang="fr" type="poet">
  <name>
    <firstname>Jean de</firstname>
    <lastname>La Fontaine</lastname>
  </name>
  <period>
    <born>
      <date>1621-07-08</date>
      <place>Château-Thierry, Frankrig</place>
    </born>
    <dead>
      <date>1695-04-13</date>
      <place>Paris</place>
    </dead>
  </period>
</person>

<person id="moliere" lang="fr" type="poet">
  <name>
    <firstname></firstname>
    <lastname>Molière</lastname>
    <realname>Jean-Baptiste Poquelin</realname>
  </name>
  <period>
    <born>
      <date>1622-01-15</date>
      <place>Paris</place>
    </born>
    <dead>
      <date>1673-02-17</date>
      <place>Paris</place>
    </dead>
  </period>
</person>

<person id="racine" lang="fr" type="poet">
  <name>
    <firstname>Jean</firstname>
    <lastname>Racine</lastname>
    <fullname>Jean-baptiste Racine</fullname>
  </name>
  <period>
    <born>
      <date>1639-12-22</date>
      <place>La Ferté-Milon, Frankrig</place><note>Dåbsdag</note>
    </born>
    <dead>
      <date>1699-04-21</date>
      <place>Paris</place>
    </dead>
  </period>
</person>

<person id="beranger" lang="fr" type="poet">
  <name>
    <firstname>Pierre-Jean de</firstname>
    <lastname>Béranger</lastname>
  </name>
  <period>
    <born>
      <date>1780-08-19</date>
      <place>Paris</place>
    </born>
    <dead>
      <date>1857-07-16</date>
      <place>Paris</place>
    </dead>
  </period>
</person>

<person id="lamartine" lang="fr" type="poet">
  <name>
    <firstname>Alphonse de</firstname>
    <lastname>Lamartine</lastname>
  </name>
  <period>
    <born>
      <date>1790-10-21</date>
      <place>Mâcon, Frankrig</place>
    </born>
    <dead>
      <date>1869-02-28</date>
      <place>Paris</place>
    </dead>
  </period>
</person>

<person id="delavigne" lang="fr" type="poet">
  <name>
    <firstname>Casimir</firstname>
    <lastname>Delavigne</lastname>
  </name>
  <period>
    <born>
      <date>1793</date>
    </born>
    <dead>
      <date>1843</date>
    </dead>
  </period>
</person>

<person id="vigny" lang="fr" type="poet">
  <name>
    <firstname>Alfred de</firstname>
    <lastname>Vigny</lastname>
    <fullname>Alfred-Victor, comte de Vigny</fullname>
  </name>
  <period>
    <born>
      <date>1797-03-27</date>
      <place>Loches, Frankrig</place>
    </born>
    <dead>
      <date>1863-09-17</date>
      <place>Paris</place>
    </dead>
  </period>
</person>

<person id="hugo" lang="fr" type="poet">
  <name>
    <firstname>Victor</firstname>
    <lastname>Hugo</lastname>
    <fullname>Victor-Marie Hugo</fullname>
  </name>
  <period>
    <born>
      <date>1802-02-26</date>
      <place>Besançon, Frankrig</place>
    </born>
    <dead>
      <date>1885-05-22</date>
      <place>Paris</place>
    </dead>
  </period>
</person>

<person id="nerval" lang="fr" type="poet">
  <name>
    <firstname>Gérard de</firstname>
    <lastname>Nerval</lastname>
    <realname>Gérard Labrunie</realname>
  </name>
  <period>
    <born>
      <date>1808-05-22</date>
      <place>Paris</place>
    </born>
    <dead>
      <date>1855-01-26</date>
      <place>Paris</place>
    </dead>
  </period>
</person>

<person id="musset" lang="fr" type="poet">
  <name>
    <firstname>Alfred de</firstname>
    <lastname>Musset</lastname>
    <fullname>Louis-Charles-Alfred de Musset</fullname>
  </name>
  <period>
    <born>
      <date>1810-12-11</date>
      <place>Paris</place>
    </born>
    <dead>
      <date>1857-05-02</date>
      <place>Paris</place>
    </dead>
  </period>
</person>

<person id="gautier" lang="fr" type="poet">
  <name>
    <firstname>Théophile</firstname>
    <lastname>Gautier</lastname>
  </name>
  <period>
    <born>
      <date>1811-08-31</date>
      <place>Tarbes, Frankrig</place>
    </born>
    <dead>
      <date>1872-10-23</date>
      <place>Neuilly-sur-Seine, Frankrig</place>
    </dead>
  </period>
</person>

<person id="baudelaire" lang="fr" type="poet">
  <name>
    <firstname>Charles</firstname>
    <lastname>Baudelaire</lastname>
    <fullname>Charles-pierre Baudelaire</fullname>
  </name>
  <period>
    <born>
      <date>1821-04-09</date>
      <place>Paris</place>
    </born>
    <dead>
      <date>1867-08-31</date>
      <place>Paris</place>
    </dead>
  </period>
</person>

<person id="mallarme" lang="fr" type="poet">
  <name>
    <firstname>Stéphane</firstname>
    <lastname>Mallarmé</lastname>
  </name>
  <period>
    <born>
      <date>1842-03-18</date>
      <place>Paris</place>
    </born>
    <dead>
      <date>1898-09-09</date>
      <place>Valvins, nær Fontainebleau, Frankrig</place>
    </dead>
  </period>
</person>

<person id="verlaine" lang="fr" type="poet">
  <name>
    <firstname>Paul</firstname>
    <lastname>Verlaine</lastname>
    <fullname>Paul-Marie Verlaine</fullname>
  </name>
  <period>
    <born>
      <date>1844-03-30</date>
      <place>Metz, Frankrig</place>
    </born>
    <dead>
      <date>1896-01-08</date>
      <place>Paris</place>
    </dead>
  </period>
</person>

<person id="lautreamont" lang="fr" type="poet">
  <name>
    <firstname>Comte de</firstname>
    <lastname>Lautréamont</lastname>
    <fullname>Isidore-Lucien Ducasse</fullname>
  </name>
  <period>
    <born>
      <date>1846-04-04</date>
      <place>Montevideo, Uruguay</place>
    </born>
    <dead>
      <date>1870-11-04</date>
      <place>Paris</place>
    </dead>
  </period>
</person>

<person id="nouveau" lang="fr" type="poet">
  <name>
    <firstname>Germain</firstname>
    <lastname>Nouveau</lastname>
  </name>
  <period>
    <born>
      <date>1851</date>
    </born>
    <dead>
      <date>1920</date>
    </dead>
  </period>
</person>

<person id="rimbaud" lang="fr" type="poet">
  <name>
    <firstname>Arthur</firstname>
    <lastname>Rimbaud</lastname>
    <fullname>Jean-Nicolas-Arthur Rimbaud</fullname>
  </name>
  <period>
    <born>
      <date>1854-10-20</date>
      <place>Charlesville, Frankrig</place>
    </born>
    <dead>
      <date>1891-11-10</date>
      <place>Marseille</place>
    </dead>
  </period>
</person>

<person id="dass" lang="no" type="poet">
  <name>
    <firstname>Peter</firstname>
    <lastname>Dass</lastname>
  </name>
  <period>
    <born>
      <date>1647</date>
    </born>
    <dead>
      <date>1707</date>
    </dead>
  </period>
</person>

<person id="tullin" lang="no" type="poet">
  <name>
    <firstname>Christian Braunman</firstname>
    <lastname>Tullin</lastname>
  </name>
  <period>
    <born>
      <date>1728-09-06</date>
    </born>
    <dead>
      <date>1765-01-21</date>
    </dead>
  </period>
</person>
 
<person id="frimannc" lang="no" type="poet">
  <name>
    <firstname>Claus</firstname>
    <lastname>Frimann</lastname>
  </name>
  <period>
    <born>
      <date>1746-05-15</date>
    </born>
    <dead>
      <date>1829-10-11</date>
    </dead>
  </period>
</person>
 
<person id="fasting" lang="no" type="poet">
  <name>
    <firstname>Claus</firstname>
    <lastname>Fasting</lastname>
  </name>
  <period>
    <born>
      <date>1746-10-29</date>
    </born>
    <dead>
      <date>1791-12-24</date>
    </dead>
  </period>
</person>
 
<person id="vibe" lang="no" type="poet">
  <name>
    <firstname>Johan</firstname>
    <lastname>Vibe</lastname>
  </name>
  <period>
    <born>
      <date>1748-09-10</date>
    </born>
    <dead>
      <date>1782-02-09</date>
    </dead>
  </period>
</person>
 
<person id="storm" lang="no" type="poet">
  <name>
    <firstname>Edvard</firstname>
    <lastname>Storm</lastname>
  </name>
  <period>
    <born>
      <date>1749-08-21</date>
    </born>
    <dead>
      <date>1794-09-29</date>
    </dead>
  </period>
</person>
 
<person id="frimannph" lang="no" type="poet">
  <name>
    <firstname>Peter Harboe</firstname>
    <lastname>Frimann</lastname>
  </name>
  <period>
    <born>
      <date>1752-11-18</date>
    </born>
    <dead>
      <date>1839-09-21</date>
    </dead>
  </period>
</person>
 
<person id="rein" lang="no" type="poet">
  <name>
    <firstname>Jonas</firstname>
    <lastname>Rein</lastname>
  </name>
  <period>
    <born>
      <date>1760-01-30</date>
    </born>
    <dead>
      <date>1821-11-21</date>
    </dead>
  </period>
</person>
 
<person id="zetlitz" lang="no" type="poet">
  <name>
    <firstname>Jens</firstname>
    <lastname>Zetlitz</lastname>
  </name>
  <period>
    <born>
      <date>1761-01-26</date>
    </born>
    <dead>
      <date>1821-01-14</date>
    </dead>
  </period>
</person>
 
<person id="schmidtf" lang="no" type="poet">
  <name>
    <firstname>Frederik</firstname>
    <lastname>Schmidt</lastname>
  </name>
  <period>
    <born>
      <date>1771-05-27</date>
    </born>
    <dead>
      <date>1840-02-16</date>
    </dead>
  </period>
</person>

<person id="bjerregaard" lang="no" type="poet">
  <name>
    <firstname>Henrik Anker</firstname>
    <lastname>Bjerregaard</lastname>
  </name>
  <period>
    <born>
      <date>1782</date>
    </born>
    <dead>
      <date>1842</date>
    </dead>
  </period>
</person>

<person id="landstad" lang="no" type="poet">
  <name>
    <firstname>Magnus Brostrup</firstname>
    <lastname>Landstad</lastname>
  </name>
  <period>
    <born>
      <date>1802</date>
    </born>
    <dead>
      <date>1880</date>
    </dead>
  </period>
</person>

<person id="welhaven" lang="no" type="poet">
  <name>
    <firstname>Johan Sebastian</firstname>
    <lastname>Welhaven</lastname>
    <fullname>Johan Sebastian Cammermeyer Welhaven</fullname>
  </name>
  <period>
    <born>
      <date>1807-12-22</date>
      <place>Bergen, Norge</place>
    </born>
    <dead>
      <date>1873-10-21</date>
      <place>Christiania (nu Oslo)</place>
    </dead>
  </period>
</person>

<person id="wergeland" lang="no" type="poet">
  <name>
    <firstname>Henrik Arnold</firstname>
    <lastname>Wergeland</lastname>
  </name>
  <period>
    <born>
      <date>1808-06-17</date>
      <place>Kristiansand, Norge</place>
    </born>
    <dead>
      <date>1845-07-12</date>
      <place>Christiania (nu Oslo)</place>
    </dead>
  </period>
</person>

<person id="munch" lang="no" type="poet">
  <name>
    <firstname>Andreas</firstname>
    <lastname>Munch</lastname>
  </name>
  <period>
    <born>
      <date>1811</date>
    </born>
    <dead>
      <date>1884</date>
    </dead>
  </period>
</person>

<person id="moe" lang="no" type="poet">
  <name>
    <firstname>Jørgen</firstname>
    <lastname>Moe</lastname>
  </name>
  <period>
    <born>
      <date>1813</date>
    </born>
    <dead>
      <date>1882</date>
    </dead>
  </period>
</person>

<person id="aasen" lang="no" type="poet">
  <name>
    <firstname>Ivar</firstname>
    <lastname>Aasen</lastname>
    <fullname>Ivar Andreas Aasen</fullname>
  </name>
  <period>
    <born>
      <date>1813-08-05</date>
      <place>Sunnmøre, Norge</place>
    </born>
    <dead>
      <date>1896-09-23</date>
      <place>Christiania (nu Oslo)</place>
    </dead>
  </period>
</person>

<person id="vinje" lang="no" type="poet">
  <name>
    <firstname>Aasmund Olavsson</firstname>
    <lastname>Vinje</lastname>
  </name>
  <period>
    <born>
      <date>1818-04-06</date>
      <place>Vinje, Norge</place>
    </born>
    <dead>
      <date>1870-07-30</date>
      <place>Gran, Norge</place>
    </dead>
  </period>
</person>

<person id="kjerulf" lang="no" type="poet">
  <name>
    <firstname>Theodor</firstname>
    <lastname>Kjerulf</lastname>
  </name>
  <period>
    <born>
      <date>1825</date>
    </born>
    <dead>
      <date>1888</date>
    </dead>
  </period>
</person>

<person id="hougen" lang="no" type="poet">
  <name>
    <firstname>Engebret</firstname>
    <lastname>Hougen</lastname>
  </name>
  <period>
    <born>
      <date>1826</date>
    </born>
    <dead>
      <date>1891</date>
    </dead>
  </period>
</person>

<person id="ibsen" lang="no" type="poet">
  <name>
    <firstname>Henrik</firstname>
    <lastname>Ibsen</lastname>
    <fullname>Henrik Johan Ibsen</fullname>
  </name>
  <period>
    <born>
      <date>1828-03-20</date>
      <place>Skien, Norge</place>
    </born>
    <dead>
      <date>1906-05-23</date>
      <place>Christiania (nu Oslo)</place>
    </dead>
  </period>
</person>

<person id="bjoernson" lang="no" type="poet">
  <name>
    <firstname>Bjørnstjerne</firstname>
    <lastname>Bjørnson</lastname>
  </name>
  <period>
    <born>
      <date>1832</date>
    </born>
    <dead>
      <date>1910</date>
    </dead>
  </period>
</person>

<person id="lie" lang="no" type="poet">
  <name>
    <firstname>Jonas</firstname>
    <lastname>Lie</lastname>
    <fullname>Jonas Lauritz Idemil Lie</fullname>
  </name>
  <period>
    <born>
      <date>1833-11-06</date>
      <place>Hokksund i Eiker, Norge</place>
    </born>
    <dead>
      <date>1908-07-05</date>
      <place>Stavern, Norge</place>
    </dead>
  </period>
</person>

<person id="sivle" lang="no" type="poet">
  <name>
    <firstname>Per</firstname>
    <lastname>Sivle</lastname>
  </name>
  <period>
    <born>
      <date>1857</date>
    </born>
    <dead>
      <date>1904</date>
    </dead>
  </period>
</person>

<person id="kinck" lang="no" type="poet">
  <name>
    <firstname>Hans Ernst</firstname>
    <lastname>Kinck</lastname>
  </name>
  <period>
    <born>
      <date>1865-10-11</date>
      <place>Øksfjord, Norge</place>
    </born>
    <dead>
      <date>1926-10-13</date>
      <place>Oslo</place>
    </dead>
  </period>
</person>

<person id="obstfelder" lang="no" type="poet">
  <name>
    <firstname>Sigbjørn</firstname>
    <lastname>Obstfelder</lastname>
  </name>
  <period>
    <born>
      <date>1866-11-21</date>
      <place>Stavanger, Norge</place>
    </born>
    <dead>
      <date>1900-07-29</date>
      <place>København</place>
    </dead>
  </period>
</person>

<person id="kjaer" lang="no" type="poet">
  <name>
    <firstname>Nils</firstname>
    <lastname>Kjær</lastname>
  </name>
  <period>
    <born>
      <date>1870</date>
    </born>
    <dead>
      <date>1924</date>
    </dead>
  </period>
</person>

<person id="aukrust" lang="no" type="poet">
  <name>
    <firstname>Olav</firstname>
    <lastname>Aukrust</lastname>
  </name>
  <period>
    <born>
      <date>1883</date>
    </born>
    <dead>
      <date>1929</date>
    </dead>
  </period>
</person>

<person id="nygard" lang="no" type="poet">
  <name>
    <firstname>Olav</firstname>
    <lastname>Nygard</lastname>
  </name>
  <period>
    <born>
      <date>1885</date>
    </born>
    <dead>
      <date>1924</date>
    </dead>
  </period>
</person>

<person id="solstad" lang="no" type="poet">
  <name>
    <firstname>Einar</firstname>
    <lastname>Solstad</lastname>
  </name>
  <period>
    <born>
      <date>1893</date>
    </born>
    <dead>
      <date>1918</date>
    </dead>
  </period>
</person>

<person id="nilsen" lang="no" type="poet">
  <name>
    <firstname>Rudolf</firstname>
    <lastname>Nilsen</lastname>
  </name>
  <period>
    <born>
      <date>1901</date>
    </born>
    <dead>
      <date>1929</date>
    </dead>
  </period>
</person>

<person id="stiernhielm" lang="se" type="poet">
  <name>
    <firstname>Georg</firstname>
    <lastname>Stiernhielm</lastname>
    <realname>Jöran Olofsson</realname>
    <alternative>Georgius Olai</alternative>
    <alternative>Göran Lilia</alternative>
  </name>
  <period>
    <born>
      <date>1598-08-07</date>
      <place>Vika, Sverige</place>
    </born>
    <dead>
      <date>1672-04-22</date>
      <place>Stockholm</place>
    </dead>
  </period>
</person>

<person id="wivallius" lang="se" type="poet">
  <name>
    <firstname>Lars</firstname>
    <lastname>Wivallius</lastname>
  </name>
  <period>
    <born>
      <date>1605</date>
      <place>Wivalla, Sverige</place>
    </born>
    <dead>
      <date>1669-04-06</date>
      <place>Stockholm</place>
    </dead>
  </period>
</person>

<person id="lucidor" lang="se" type="poet">
  <name>
    <firstname>Lars (Lucidor)</firstname>
    <lastname>Johansson</lastname>
    <pseudonym>Lucidor</pseudonym>
  </name>
  <period>
    <born>
      <date>1638-10-18</date>
      <place>Stockholm</place>
    </born>
    <dead>
      <date>1674-08-13</date>
      <place>Stockholm</place>
    </dead>
  </period>
</person>

<person id="columbus" lang="se" type="poet">
  <name>
    <firstname>Samuel</firstname>
    <lastname>Columbus</lastname>
  </name>
  <period>
    <born>
      <date>1642</date>
    </born>
    <dead>
      <date>1679</date>
    </dead>
  </period>
</person>

<person id="bergbo" lang="se" type="poet">
  <name>
    <firstname>Skogekär</firstname>
    <lastname>Bergbo</lastname>
  </name>
  <period>
    <born>
      <date>?</date>
    </born>
    <dead>
      <date>?</date>
    </dead>
  </period>
</person>

<person id="spegel" lang="se" type="poet">
  <name>
    <firstname>Haquin</firstname>
    <lastname>Spegel</lastname>
  </name>
  <period>
    <born>
      <date>1645</date>
    </born>
    <dead>
      <date>1713</date>
    </dead>
  </period>
</person>

<person id="runius" lang="se" type="poet">
  <name>
    <firstname>Johan</firstname>
    <lastname>Runius</lastname>
  </name>
  <period>
    <born>
      <date>1679</date>
    </born>
    <dead>
      <date>1713</date>
    </dead>
  </period>
</person>

<person id="brenner" lang="se" type="poet">
  <name>
    <firstname>Sophia Elisabet</firstname>
    <lastname>Brenner</lastname>
  </name>
  <period>
    <born>
      <date>1659</date>
    </born>
    <dead>
      <date>1730</date>
    </dead>
  </period>
</person>

<person id="frese" lang="se" type="poet">
  <name>
    <firstname>Jakob</firstname>
    <lastname>Frese</lastname>
  </name>
  <period>
    <born>
      <date>ca. 1690</date>
    </born>
    <dead>
      <date>1729</date>
    </dead>
  </period>
</person>

<person id="dalin" lang="se" type="poet">
  <name>
    <firstname>Olof von</firstname>
    <lastname>Dalin</lastname>
  </name>
  <period>
    <born>
      <date>1708-08-29</date>
      <place>Vinberg, Sverige</place>
    </born>
    <dead>
      <date>1763-08-12</date>
      <place>Stockholm</place>
    </dead>
  </period>
</person>

<person id="nordenflycht" lang="se" type="poet">
  <name>
    <firstname>Hedvig Charlotta</firstname>
    <lastname>Nordenflycht</lastname>
  </name>
  <period>
    <born>
      <date>1718-11-28</date>
      <place>Stockholm</place>
    </born>
    <dead>
      <date>1763-06-29</date>
      <place>Lugnet nær Stockholm</place>
    </dead>
  </period>
</person>

<person id="creutz" lang="se" type="poet">
  <name>
    <firstname>Gustaf Philip</firstname>
    <lastname>Creutz</lastname>
    <fullname>Gustav Philip, Greve Creutz</fullname>
  </name>
  <period>
    <born>
      <date>1731-05-01</date>
      <place>Anjala, Svensk Finland (nu Finland)</place>
    </born>
    <dead>
      <date>1785-10-30</date>
      <place>Stockholm</place>
    </dead>
  </period>
</person>

<person id="bellman" lang="se" type="poet">
  <name>
    <firstname>Carl Michael</firstname>
    <lastname>Bellman</lastname>
  </name>
  <period>
    <born>
      <date>1740-02-04</date>
      <place>Stockholm</place>
    </born>
    <dead>
      <date>1795-02-11</date>
      <place>Stockholm</place>
    </dead>
  </period>
</person>

<person id="stagnelius" lang="se" type="poet">
  <name>
    <firstname>Erik Johan</firstname>
    <lastname>Stagnelius</lastname>
  </name>
  <period>
    <born>
      <date>1793-10-14</date>
      <place>Öland, Sverige</place>
    </born>
    <dead>
      <date>1823-04-03</date>
      <place>Stockholm</place>
    </dead>
  </period>
</person>

<person id="rydberg" lang="se" type="poet">
  <name>
    <firstname>Viktor</firstname>
    <lastname>Rydberg</lastname>
    <fullname>Abraham Viktor Rydberg</fullname>
  </name>
  <period>
    <born>
      <date>1828-12-18</date>
      <place>Jönköbing, Sverige</place>
    </born>
    <dead>
      <date>1895-09-21</date>
      <place>Djursholm, Sverige</place>
    </dead>
  </period>
</person>

<person id="snoilsky" lang="se" type="poet">
  <name>
    <firstname>Carl</firstname>
    <lastname>Snoilsky</lastname>
    <fullname>Carl Johan Gustaf, Greve Snoilsky</fullname>
  </name>
  <period>
    <born>
      <date>1841-09-08</date>
      <place>Stockholm</place>
    </born>
    <dead>
      <date>1903-05-19</date>
      <place>Stockholm</place>
    </dead>
  </period>
</person>

<person id="langland" lang="uk" type="poet">
  <name>
    <firstname>William</firstname>
    <lastname>Langland</lastname>
  </name>
  <period>
    <born>
      <date>1330?</date>
    </born>
    <dead>
      <date>1400?</date>
    </dead>
  </period>
</person>

<person id="chaucer" lang="uk" type="poet">
  <name>
    <firstname>Geoffrey</firstname>
    <lastname>Chaucer</lastname>
  </name>
  <period>
    <born>
      <date>1342/43</date>
      
    </born>
    <dead>
      <date>1400-10-25</date>
      <place>London</place>
    </dead>
  </period>
</person>

<person id="spenser" lang="uk" type="poet">
  <name>
    <firstname>Edmund</firstname>
    <lastname>Spenser</lastname>
  </name>
  <period>
    <born>
      <date>1522</date>
      <place>London</place>
    </born>
    <dead>
      <date>1599-01-13</date>
      <place>London</place>
    </dead>
  </period>
</person>

<person id="shakespeare" lang="uk" type="poet">
  <name>
    <firstname>William</firstname>
    <lastname>Shakespeare</lastname>
  </name>
  <period>
    <born>
      <date>1564-04-26</date>
      <place>Stratford-upon-Avon, Warwickshire, England</place>
      <note>Dåbsdag</note>
    </born>
    <dead>
      <date>1616-04-23</date>
      <place>Stratford-upon-Avon, Warwickshire, England</place>
    </dead>
  </period>
</person>

<person id="campion" lang="uk" type="poet">
  <name>
    <firstname>Thomas</firstname>
    <lastname>Campion</lastname>
  </name>
  <period>
    <born>
      <date>1567-02-12</date>
      <place>London</place>
    </born>
    <dead>
      <date>1620-03-01</date>
    </dead>
  </period>
</person>

<person id="donne" lang="uk" type="poet">
  <name>
    <firstname>John</firstname>
    <lastname>Donne</lastname>
  </name>
  <period>
    <born>
      <date>1572</date>
    </born>
    <dead>
      <date>1631-03-31</date>
      <place>London</place>
    </dead>
  </period>
</person>

<person id="milton" lang="uk" type="poet">
  <name>
    <firstname>John</firstname>
    <lastname>Milton</lastname>
  </name>
  <period>
    <born>
      <date>1608-12-09</date>
      <place>London</place>
    </born>
    <dead>
      <date>1674-11-08</date>
      <place>Chalfont St. Giles, Buckinghamshire, England</place>
    </dead>
  </period>
</person>

<person id="lovelace" lang="uk" type="poet">
  <name>
    <firstname>Richard</firstname>
    <lastname>Lovelace</lastname>
  </name>
  <period>
    <born>
      <date>1618</date>
      
    </born>
    <dead>
      <date>1657</date>
      <place>London</place>
    </dead>
  </period>
</person>

<person id="dryden" lang="uk" type="poet">
  <name>
    <firstname>John</firstname>
    <lastname>Dryden</lastname>
  </name>
  <period>
    <born>
      <date>1631-08-09</date>
      <place>Aldwinkle, Northamptonshire, England</place>
    </born>
    <dead>
      <date>1700-05-01</date>
      <place>London</place>
    </dead>
  </period>
</person>

<person id="swift" lang="uk" type="poet">
  <name>
    <firstname>Jonathan</firstname>
    <lastname>Swift</lastname>
  </name>
  <period>
    <born>
      <date>1667-11-30</date>
      <place>Dublin</place>
    </born>
    <dead>
      <date>1745-10.19</date>
      <place>Dublin</place>
    </dead>
  </period>
</person>

<person id="young" lang="uk" type="poet">
  <name>
    <firstname>Edward</firstname>
    <lastname>Young</lastname>
  </name>
  <period>
    <born>
      <date>1683-07-03</date>
      <place>Upham, Hampshire, England</place>
    </born>
    <dead>
      <date>1765-04-05</date>
      <place>Welwyn, Hertfordshire, England</place>
    </dead>
  </period>
</person>

<person id="pope" lang="uk" type="poet">
  <name>
    <firstname>Alexander</firstname>
    <lastname>Pope</lastname>
  </name>
  <period>
    <born>
      <date>1688-05-21</date>
      <place>London</place>
    </born>
    <dead>
      <date>1744-05-30</date>
      <place>Twickenham, England</place>
    </dead>
  </period>
</person>

<person id="thomson" lang="uk" type="poet">
  <name>
    <firstname>James</firstname>
    <lastname>Thomson</lastname>
  </name>
  <period>
    <born>
      <date>1700-09-11</date>
      <place>Ednam, Roxburgh, Skotland</place>
    </born>
    <dead>
      <date>1748-08-27</date>
      <place>Richmond, England</place>
    </dead>
  </period>
</person>

<person id="gray" lang="uk" type="poet">
  <name>
    <firstname>Thomas</firstname>
    <lastname>Gray</lastname>
  </name>
  <period>
    <born>
      <date>1716-12-26</date>
      <place>London</place>
    </born>
    <dead>
      <date>1771-07-30</date>
      <place>Cambridge, Cambridgeshire, England</place>
    </dead>
  </period>
</person>

<person id="macpherson" lang="uk" type="poet">
  <name>
    <firstname>James</firstname>
    <lastname>MacPherson</lastname>
  </name>
  <period>
    <born>
      <date>1736-10-27</date>
      <place>Ruthven, Inverness, Skotland</place>
    </born>
    <dead>
      <date>1796-02-17</date>
      <place>Belville, Inverness, Skotland</place>
    </dead>
  </period>
</person>

<person id="blake" lang="uk" type="poet">
  <name>
    <firstname>William</firstname>
    <lastname>Blake</lastname>
  </name>
  <period>
    <born>
      <date>1757-11-28</date>
      <place>London</place>
    </born>
    <dead>
      <date>1827-08-12</date>
      <place>London</place>
    </dead>
  </period>
</person>

<person id="burns" lang="uk" type="poet">
  <name>
    <firstname>Robert</firstname>
    <lastname>Burns</lastname>
  </name>
  <period>
    <born>
      <date>1759-01-25</date>
      <place>Alloway, Ayrshire, Skotland</place>
    </born>
    <dead>
      <date>1796-07-21</date>
      <place>Dumfries, Dumfriesshire, England</place>
    </dead>
  </period>
</person>

<person id="wordsworth" lang="uk" type="poet">
  <name>
    <firstname>William</firstname>
    <lastname>Wordsworth</lastname>
  </name>
  <period>
    <born>
      <date>1770-04-07</date>
      <place>Cockermouth, Cumberland, England</place>
    </born>
    <dead>
      <date>1850-04-23</date>
      <place>Rydal Mount, Westmorland, England</place>
    </dead>
  </period>
</person>

<person id="scott" lang="uk" type="poet">
  <name>
    <firstname>Sir Walter</firstname>
    <lastname>Scott</lastname>
  </name>
  <period>
    <born>
      <date>1771-08-15</date>
      <place>Edinburgh</place>
    </born>
    <dead>
      <date>1832-09-21</date>
      <place>Abbotsford, Roxburgh, Scotland</place>
    </dead>
  </period>
</person>

<person id="montgomery" lang="uk" type="poet">
  <name>
    <firstname>James</firstname>
    <lastname>Montgomery</lastname>
  </name>
  <period>
    <born>
      <date>1771-11-04</date>
      <place> Irvine, Ayrshire, Skotland</place>
    </born>
    <dead>
      <date>1854-04-30</date>
      <place>Sheffield, Yorkshire, England</place>
    </dead>
  </period>
</person>

<person id="coleridge" lang="uk" type="poet">
  <name>
    <firstname>Samuel Taylor</firstname>
    <lastname>Coleridge</lastname>
  </name>
  <period>
    <born>
      <date>1772-10-21</date>
      <place>Ottery St. Mary, Devonshire, England</place>
    </born>
    <dead>
      <date>1834-07-25</date>
      <place>Highgate, ved London</place>
    </dead>
  </period>
</person>

<person id="moore" lang="uk" type="poet">
  <name>
    <firstname>Thomas</firstname>
    <lastname>Moore</lastname>
  </name>
  <period>
    <born>
      <date>1779-05-28</date>
      <place>Dublin</place>
    </born>
    <dead>
      <date>1852-02-25</date>
      <place>Wiltshire, England</place>
    </dead>
  </period>
</person>

<person id="byron" lang="uk" type="poet">
  <name>
    <firstname>George Gordon</firstname>
    <lastname>Byron</lastname>
    <fullname>George Gordon Byron, 6th Baron</fullname>
  </name>
  <period>
    <born>
      <date>1788-01-22</date>
      <place>London</place>
    </born>
    <dead>
      <date>1824-04-19</date>
      <place>Missolonghi, Grækenland</place>
    </dead>
  </period>
</person>

<person id="shelley" lang="uk" type="poet">
  <name>
    <firstname>Percy Bysshe</firstname>
    <lastname>Shelley</lastname>
  </name>
  <period>
    <born>
      <date>1792-08-04</date>
      <place>Field Place, ved Horsham, Sussex, England</place>
    </born>
    <dead>
      <date>1822-07-08</date>
      <place>Liverno, Italien</place>
    </dead>
  </period>
</person>

<person id="keats" lang="uk" type="poet">
  <name>
    <firstname>John</firstname>
    <lastname>Keats</lastname>
  </name>
  <period>
    <born>
      <date>1795-10-31</date>
      <place>London</place>
    </born>
    <dead>
      <date>1821-02-23</date>
      <place>Rom</place>
    </dead>
  </period>
</person>

<person id="browningeb" lang="uk" type="poet">
  <name>
    <firstname>Elizabeth Barrett</firstname>
    <lastname>Browning</lastname>
  </name>
  <period>
    <born>
      <date>1806-03-06</date>
      <place>Durham, England</place>
    </born>
    <dead>
      <date>1861-06-29</date>
      <place>Firenze</place>
    </dead>
  </period>
</person>

<person id="longfellow" lang="us" type="poet">
  <name>
    <firstname>Henry Wadsworth</firstname>
    <lastname>Longfellow</lastname>
  </name>
  <period>
    <born>
      <date>1807-02-27</date>
      <place>Portland, Mass. (nu i Maine), USA</place>
    </born>
    <dead>
      <date>1882-03-24</date>
      <place>Cambridge, Mass., USA</place>
    </dead>
  </period>
</person>

<person id="poe" lang="us" type="poet">
  <name>
    <firstname>Edgar Allan</firstname>
    <lastname>Poe</lastname>
  </name>
  <period>
    <born>
      <date>1809-01-19</date>
      <place>Boston, Mass., USA</place>
    </born>
    <dead>
      <date>1849-10-07</date>
      <place>Baltimore, Md., USA</place>
    </dead>
  </period>
</person>

<person id="tennyson" lang="uk" type="poet">
  <name>
    <firstname>Alfred Lord</firstname>
    <lastname>Tennyson</lastname>
  </name>
  <period>
    <born>
      <date>1809-08-06</date>
      <place>Somersby, Lincolnshire, England</place>
    </born>
    <dead>
      <date>1892-10-06</date>
      <place>Aldworth, Surrey, England</place>
    </dead>
  </period>
</person>

<person id="browningr" lang="uk" type="poet">
  <name>
    <firstname>Robert</firstname>
    <lastname>Browning</lastname>
  </name>
  <period>
    <born>
      <date>1812-05-07</date>
      <place>London</place>
    </born>
    <dead>
      <date>1889-12-12</date>
      <place>Venedig</place>
    </dead>
  </period>
</person>

<person id="emerson" lang="us" type="poet">
  <name>
    <firstname>Ralph Waldo</firstname>
    <lastname>Emerson</lastname>
  </name>
  <period>
    <born>
      <date>1803-05-25</date>
      <place>Boston, Mass.</place>
    </born>
    <dead>
      <date>1882-04-27</date>
      <place>Concord, Mass.</place>
    </dead>
  </period>
</person>

<person id="freneau" lang="us" type="poet">
  <name>
    <firstname>Philip</firstname>
    <lastname>Freneau</lastname>
    <fullname>Philip Morin Freneau</fullname>
  </name>
  <period>
    <born>
      <date>1752-01-02</date>
      <place>New York</place>
    </born>
    <dead>
      <date>1832-12-18</date>
      <place>Monmouth county, N.J., USA</place>
    </dead>
  </period>
</person>

<person id="whitman" lang="us" type="poet">
  <name>
    <firstname>Walt</firstname>
    <lastname>Whitman</lastname>
  </name>
  <period>
    <born>
      <date>1819-05-31</date>
      <place>West Hills, Long Island, New York, USA</place>
    </born>
    <dead>
      <date>1892-03-26</date>
      <place>Camden, New Jersey, USA</place>
    </dead>
  </period>
</person>

<person id="rossettid" lang="uk" type="poet">
  <name>
    <firstname>Dante Gabriel</firstname>
    <lastname>Rossetti</lastname>
  </name>
  <period>
    <born>
      <date>1828-05-12</date>
      <place>London</place>
    </born>
    <dead>
      <date>1882-04-09</date>
      <place>Birchington-on-Sea, Kent, England</place>
    </dead>
  </period>
</person>

<person id="dickinson" lang="us" type="poet">
  <name>
    <firstname>Emily</firstname>
    <lastname>Dickinson</lastname>
  </name>
  <period>
    <born>
      <date>1830-12-10</date>
      <place>Amherst, Mass., USA</place>
    </born>
    <dead>
      <date>1886-05-15</date>
      <place>Amherst, Mass., USA</place>
    </dead>
  </period>
</person>

<person id="rossettic" lang="uk" type="poet">
  <name>
    <firstname>Christina</firstname>
    <lastname>Rossetti</lastname>
  </name>
  <period>
    <born>
      <date>1830-12-05</date>
      <place>London</place>
    </born>
    <dead>
      <date>1894-12-29</date>
      <place>London</place>
    </dead>
  </period>
</person>

<person id="carrol" lang="uk" type="poet">
  <name>
    <firstname>Lewis</firstname>
    <lastname>Carroll</lastname>
    <realname>Charles Lutwidge Dodgson</realname>
  </name>
  <period>
    <born>
      <date>1832-01-27</date>
      <place>Daresbury, Cheshire, England</place>
    </born>
    <dead>
      <date>1898-01-14</date>
      <place>Guildford, Surrey, England</place>
    </dead>
  </period>
</person>

<person id="kipling" lang="uk" type="poet">
  <name>
    <firstname>Rudyard</firstname>
    <lastname>Kipling</lastname>
  </name>
  <period>
    <born>
      <date>1865-12-30</date>
      <place>Bombay, Indien</place>
    </born>
    <dead>
      <date>1936-01-18</date>
      <place>London</place>
    </dead>
  </period>
</person>

<person id="hardy" lang="uk" type="poet">
  <name>
    <firstname>Thomas</firstname>
    <lastname>Hardy</lastname>
  </name>
  <period>
    <born>
      <date>1840-06-02</date>
      <place>Higher Bockhampton, Dorset, England</place>
    </born>
    <dead>
      <date>1928-01-11</date>
      <place>Dorchester, Dorset, England</place>
    </dead>
  </period>
</person>

<person id="hopkins" lang="uk" type="poet">
  <name>
    <firstname>Gerard Manley</firstname>
    <lastname>Hopkins</lastname>
  </name>
  <period>
    <born>
      <date>1844-07-28</date>
      <place>Stratford, Essex, England</place>
    </born>
    <dead>
      <date>1889-06-08</date>
      <place>Dublin</place>
    </dead>
  </period>
</person>

<person id="wilde" lang="uk" type="poet">
  <name>
    <firstname>Oscar</firstname>
    <lastname>Wilde</lastname>
    <realname>Fingal O'Flahertie Wills</realname>
  </name>
  <period>
    <born>
      <date>1854-10-16</date>
      <place>Dublin</place>
    </born>
    <dead>
      <date>1900-11-30</date>
      <place>Paris</place>
    </dead>
  </period>
</person>

<person id="yeats" lang="uk" type="poet">
  <name>
    <firstname>W. B.</firstname>
    <lastname>Yeats</lastname>
    <fullname>William Butler Yeats</fullname>
  </name>
  <period>
    <born>
      <date>1865-06-13</date>
      <place>Sandymount, Dublin</place>
    </born>
    <dead>
      <date>1939-01-28</date>
      <place>Roquebrune-Cap-Martin, Frankrig</place>
    </dead>
  </period>
</person>

<person id="lawrence" lang="uk" type="poet">
  <name>
    <firstname>D. H.</firstname>
    <lastname>Lawrence</lastname>
    <fullname>David Herbert Lawrence</fullname>
  </name>
  <period>
    <born>
      <date>1885-09-11</date>
      <place>Eastwood, Nottinghamshire, England</place>
    </born>
    <dead>
      <date>1930-03-02</date>
      <place>Vence, Frankrig</place>
    </dead>
  </period>
</person>

<person id="brooke" lang="uk" type="poet">
  <name>
    <firstname>Rupert</firstname>
    <lastname>Brooke</lastname>
  </name>
  <period>
    <born>
      <date>1887-08-03</date>
      <place>Rugby, Warwickshire, England</place>
    </born>
    <dead>
      <date>1915-04-23</date>
      <place>Skyros, Grækenland</place>
    </dead>
  </period>
</person>

<person id="bradstreet" lang="us" type="poet">
  <name>
    <firstname>Anne</firstname>
    <lastname>Bradstreet</lastname>
  </name>
  <period>
    <born>
      <date>1612</date>
      <place>Northampton, Northamptonshire?, England</place>
    </born>
    <dead>
      <date>1672-09-16</date>
      <place>Andover, Massachusetts Bay Colony (USA)</place>
    </dead>
  </period>
</person>

</persons>
