<?xml version="1.0" encoding="UTF-8"?>
<person id="weyse" country="dk" lang="da" type="poet">
  <name>
    <firstname>C.E.F</firstname>
    <lastname>Weyse</lastname>
    <fullname>Christoph Ernst Friedrich Weyse</fullname>
  </name>
  <period>
    <born>
      <date>1774-03-05</date>
      <place>Altona</place>
    </born>
    <dead>
      <date>1842-10-08</date>
      <place>København</place>
    </dead>
  </period>
  <works>andre</works>
  <identifiers>
    <wikidata>Q707924</wikidata>
    <wikipedia-da>C.E.F. Weyse</wikipedia-da>
    <wikipedia-en>Christoph Ernst Friedrich Weyse</wikipedia-en>
    <wikipedia-fr>Christoph Ernst Friedrich Weyse</wikipedia-fr>
    <wikipedia-de>Christoph Ernst Friedrich Weyse</wikipedia-de>
    <gravsted-dk>weyse</gravsted-dk>
    <viaf>12495676</viaf>
    <lex-dk>C.E.F._Weyse</lex-dk>
    <biografisk-leksikon-lex-dk>C.E.F._Weyse</biografisk-leksikon-lex-dk>
    <litteraturpriser-dk>WCEFWeyse</litteraturpriser-dk>
    <runeberg-org>weysecri</runeberg-org>
  </identifiers>
</person>
