<?xml version="1.0" encoding="UTF-8"?>
<person id="birkerod" country="dk" lang="da" type="poet">
  <name>
    <firstname>C.V.P.</firstname>
    <lastname>Birkerod</lastname>
    <fullname>Carl Vilhelm Peter Birkerod</fullname>
  </name>
  <period>
    <born>
      <date>1795-03-03</date>
    </born>
    <dead>
      <date>1820-01-06</date>
      <place>Odense</place>
    </dead>
  </period>
  <!-- Søn af Kjøbmand A. B. i Odense. Død 6. Januar 1820 i Odense. Kilde: Erslew: Almindeligt forfatter-lexicon. Bind 1-6, 1843-68: bind suppl. 1, side 158. -->
  <works>1816,andre</works>
</person>
